{
"meta":{"test_sets":[],"test_metrics":[],"learn_metrics":[{"best_value":"Min","name":"RMSE"}],"launch_mode":"Train","parameters":"","iteration_count":1000,"learn_sets":["learn"],"name":"experiment"},
"iterations":[
{"learn":[14.59871775],"iteration":0,"passed_time":0.07624647922,"remaining_time":76.17023274},
{"learn":[14.22518863],"iteration":1,"passed_time":0.07762334799,"remaining_time":38.73405065},
{"learn":[13.8866124],"iteration":2,"passed_time":0.07886279968,"remaining_time":26.20873709},
{"learn":[13.52356875],"iteration":3,"passed_time":0.08018938074,"remaining_time":19.9671558},
{"learn":[13.18870211],"iteration":4,"passed_time":0.0814509039,"remaining_time":16.20872988},
{"learn":[12.9124226],"iteration":5,"passed_time":0.08272815076,"remaining_time":13.70529698},
{"learn":[12.60003351],"iteration":6,"passed_time":0.08406998129,"remaining_time":11.92592735},
{"learn":[12.32990573],"iteration":7,"passed_time":0.08537692015,"remaining_time":10.5867381},
{"learn":[12.0660619],"iteration":8,"passed_time":0.08670225794,"remaining_time":9.546881958},
{"learn":[11.77309809],"iteration":9,"passed_time":0.08775231176,"remaining_time":8.687478865},
{"learn":[11.49227636],"iteration":10,"passed_time":0.09008136196,"remaining_time":8.099133362},
{"learn":[11.26264833],"iteration":11,"passed_time":0.09142773347,"remaining_time":7.527550056},
{"learn":[11.04260393],"iteration":12,"passed_time":0.09259517808,"remaining_time":7.030110828},
{"learn":[10.79916926],"iteration":13,"passed_time":0.09383393232,"remaining_time":6.608589805},
{"learn":[10.5541002],"iteration":14,"passed_time":0.09503621048,"remaining_time":6.240711155},
{"learn":[10.31918115],"iteration":15,"passed_time":0.09634488789,"remaining_time":5.925210606},
{"learn":[10.10004441],"iteration":16,"passed_time":0.09812505314,"remaining_time":5.673936896},
{"learn":[9.894556723],"iteration":17,"passed_time":0.09938634971,"remaining_time":5.422077523},
{"learn":[9.690174082],"iteration":18,"passed_time":0.100735447,"remaining_time":5.201130184},
{"learn":[9.506034866],"iteration":19,"passed_time":0.1035131192,"remaining_time":5.072142842},
{"learn":[9.338524633],"iteration":20,"passed_time":0.1051031883,"remaining_time":4.899810541},
{"learn":[9.170203312],"iteration":21,"passed_time":0.1064722673,"remaining_time":4.733176244},
{"learn":[9.010299969],"iteration":22,"passed_time":0.1079424017,"remaining_time":4.5852055},
{"learn":[8.843866678],"iteration":23,"passed_time":0.1094422771,"remaining_time":4.450652601},
{"learn":[8.690548059],"iteration":24,"passed_time":0.1110514417,"remaining_time":4.331006226},
{"learn":[8.555307687],"iteration":25,"passed_time":0.1124459943,"remaining_time":4.212399939},
{"learn":[8.413851302],"iteration":26,"passed_time":0.1139211153,"remaining_time":4.105379452},
{"learn":[8.29256019],"iteration":27,"passed_time":0.1155290004,"remaining_time":4.01050673},
{"learn":[8.162193833],"iteration":28,"passed_time":0.1177184713,"remaining_time":3.94153916},
{"learn":[8.040736294],"iteration":29,"passed_time":0.1192833987,"remaining_time":3.85682989},
{"learn":[7.921220278],"iteration":30,"passed_time":0.1208184857,"remaining_time":3.776552022},
{"learn":[7.809589039],"iteration":31,"passed_time":0.1224285415,"remaining_time":3.703463382},
{"learn":[7.699675801],"iteration":32,"passed_time":0.1239767032,"remaining_time":3.632893091},
{"learn":[7.60645267],"iteration":33,"passed_time":0.1256894984,"remaining_time":3.571060454},
{"learn":[7.498880302],"iteration":34,"passed_time":0.1272752607,"remaining_time":3.509160758},
{"learn":[7.401158744],"iteration":35,"passed_time":0.1289237173,"remaining_time":3.452290651},
{"learn":[7.306431077],"iteration":36,"passed_time":0.1303909702,"remaining_time":3.393689304},
{"learn":[7.223863468],"iteration":37,"passed_time":0.1329924227,"remaining_time":3.366808175},
{"learn":[7.143477682],"iteration":38,"passed_time":0.1350660973,"remaining_time":3.328167168},
{"learn":[7.062817131],"iteration":39,"passed_time":0.1366919206,"remaining_time":3.280606095},
{"learn":[6.990793435],"iteration":40,"passed_time":0.1382354689,"remaining_time":3.233361333},
{"learn":[6.931862224],"iteration":41,"passed_time":0.1400472197,"remaining_time":3.194410392},
{"learn":[6.858296558],"iteration":42,"passed_time":0.1417708126,"remaining_time":3.15522483},
{"learn":[6.786268161],"iteration":43,"passed_time":0.1435601954,"remaining_time":3.119171519},
{"learn":[6.717118549],"iteration":44,"passed_time":0.1469642289,"remaining_time":3.118907525},
{"learn":[6.652948106],"iteration":45,"passed_time":0.1487742892,"remaining_time":3.085449389},
{"learn":[6.589686076],"iteration":46,"passed_time":0.1503072056,"remaining_time":3.047718445},
{"learn":[6.531283097],"iteration":47,"passed_time":0.1520541242,"remaining_time":3.01574013},
{"learn":[6.471368031],"iteration":48,"passed_time":0.1536451426,"remaining_time":2.981970013},
{"learn":[6.416481395],"iteration":49,"passed_time":0.1551181705,"remaining_time":2.947245239},
{"learn":[6.369870822],"iteration":50,"passed_time":0.1567131731,"remaining_time":2.916094142},
{"learn":[6.325678067],"iteration":51,"passed_time":0.1583355799,"remaining_time":2.886579418},
{"learn":[6.275766122],"iteration":52,"passed_time":0.1610853105,"remaining_time":2.878260171},
{"learn":[6.224773967],"iteration":53,"passed_time":0.1628008845,"remaining_time":2.85203031},
{"learn":[6.182249254],"iteration":54,"passed_time":0.1642676472,"remaining_time":2.822416847},
{"learn":[6.139904173],"iteration":55,"passed_time":0.1657886607,"remaining_time":2.794723137},
{"learn":[6.100525536],"iteration":56,"passed_time":0.1674326125,"remaining_time":2.769981642},
{"learn":[6.062568564],"iteration":57,"passed_time":0.1690439284,"remaining_time":2.745506562},
{"learn":[6.030559288],"iteration":58,"passed_time":0.1706076875,"remaining_time":2.721048032},
{"learn":[5.997931376],"iteration":59,"passed_time":0.1721517302,"remaining_time":2.697043773},
{"learn":[5.964103835],"iteration":60,"passed_time":0.1752227955,"remaining_time":2.697282049},
{"learn":[5.933729724],"iteration":61,"passed_time":0.1767476054,"remaining_time":2.674020224},
{"learn":[5.901932711],"iteration":62,"passed_time":0.1783295654,"remaining_time":2.652298457},
{"learn":[5.873727795],"iteration":63,"passed_time":0.1800063242,"remaining_time":2.632592491},
{"learn":[5.846485734],"iteration":64,"passed_time":0.1816401209,"remaining_time":2.612823278},
{"learn":[5.820630862],"iteration":65,"passed_time":0.1832770251,"remaining_time":2.593647597},
{"learn":[5.793646238],"iteration":66,"passed_time":0.1849433541,"remaining_time":2.575405215},
{"learn":[5.765388646],"iteration":67,"passed_time":0.1865493162,"remaining_time":2.556822981},
{"learn":[5.747073912],"iteration":68,"passed_time":0.189154609,"remaining_time":2.552216535},
{"learn":[5.722315217],"iteration":69,"passed_time":0.1908434719,"remaining_time":2.535491842},
{"learn":[5.699970599],"iteration":70,"passed_time":0.1926564618,"remaining_time":2.520814831},
{"learn":[5.682732647],"iteration":71,"passed_time":0.1943400451,"remaining_time":2.504827248},
{"learn":[5.663525791],"iteration":72,"passed_time":0.1959900448,"remaining_time":2.48880509},
{"learn":[5.642381613],"iteration":73,"passed_time":0.1974274095,"remaining_time":2.470510556},
{"learn":[5.621404779],"iteration":74,"passed_time":0.1989469068,"remaining_time":2.453678517},
{"learn":[5.602460129],"iteration":75,"passed_time":0.2005513721,"remaining_time":2.438282471},
{"learn":[5.587337574],"iteration":76,"passed_time":0.2020577931,"remaining_time":2.42206939},
{"learn":[5.572393026],"iteration":77,"passed_time":0.2049895453,"remaining_time":2.423081549},
{"learn":[5.558425806],"iteration":78,"passed_time":0.2068972337,"remaining_time":2.412055091},
{"learn":[5.541518902],"iteration":79,"passed_time":0.2087654111,"remaining_time":2.400802227},
{"learn":[5.526157283],"iteration":80,"passed_time":0.2104781683,"remaining_time":2.388017737},
{"learn":[5.511746977],"iteration":81,"passed_time":0.2124365538,"remaining_time":2.378253126},
{"learn":[5.504975022],"iteration":82,"passed_time":0.2133316305,"remaining_time":2.356928978},
{"learn":[5.493980522],"iteration":83,"passed_time":0.2148073362,"remaining_time":2.342422856},
{"learn":[5.480745463],"iteration":84,"passed_time":0.2161702341,"remaining_time":2.327008991},
{"learn":[5.464052013],"iteration":85,"passed_time":0.2181322441,"remaining_time":2.318289199},
{"learn":[5.449143727],"iteration":86,"passed_time":0.2199310475,"remaining_time":2.308012027},
{"learn":[5.438255432],"iteration":87,"passed_time":0.2212898088,"remaining_time":2.293367109},
{"learn":[5.425927931],"iteration":88,"passed_time":0.2227369983,"remaining_time":2.279925904},
{"learn":[5.412331217],"iteration":89,"passed_time":0.2239527798,"remaining_time":2.26441144},
{"learn":[5.400691499],"iteration":90,"passed_time":0.22530731,"remaining_time":2.250597196},
{"learn":[5.391618744],"iteration":91,"passed_time":0.2267118947,"remaining_time":2.23754783},
{"learn":[5.380766572],"iteration":92,"passed_time":0.2280561006,"remaining_time":2.224160035},
{"learn":[5.372207183],"iteration":93,"passed_time":0.2294447215,"remaining_time":2.211456571},
{"learn":[5.362918837],"iteration":94,"passed_time":0.2307428016,"remaining_time":2.198128794},
{"learn":[5.348292324],"iteration":95,"passed_time":0.2320174019,"remaining_time":2.184830535},
{"learn":[5.339772295],"iteration":96,"passed_time":0.2350704103,"remaining_time":2.188335882},
{"learn":[5.331515983],"iteration":97,"passed_time":0.2367442656,"remaining_time":2.179013547},
{"learn":[5.323861644],"iteration":98,"passed_time":0.2380328342,"remaining_time":2.166339228},
{"learn":[5.313277281],"iteration":99,"passed_time":0.2394172628,"remaining_time":2.154755365},
{"learn":[5.30685627],"iteration":100,"passed_time":0.2407627735,"remaining_time":2.143027063},
{"learn":[5.29652059],"iteration":101,"passed_time":0.2421752634,"remaining_time":2.132092024},
{"learn":[5.288350766],"iteration":102,"passed_time":0.2435029293,"remaining_time":2.120603181},
{"learn":[5.27993346],"iteration":103,"passed_time":0.2448432757,"remaining_time":2.10941899},
{"learn":[5.271789139],"iteration":104,"passed_time":0.2461975903,"remaining_time":2.098541365},
{"learn":[5.262684686],"iteration":105,"passed_time":0.24848951,"remaining_time":2.09575115},
{"learn":[5.251619772],"iteration":106,"passed_time":0.2503193379,"remaining_time":2.089113727},
{"learn":[5.241012171],"iteration":107,"passed_time":0.2516495966,"remaining_time":2.07843926},
{"learn":[5.232684032],"iteration":108,"passed_time":0.2530613199,"remaining_time":2.068602166},
{"learn":[5.224267141],"iteration":109,"passed_time":0.2544955966,"remaining_time":2.059100736},
{"learn":[5.216324968],"iteration":110,"passed_time":0.2558750008,"remaining_time":2.049305186},
{"learn":[5.211102527],"iteration":111,"passed_time":0.2573536588,"remaining_time":2.040446866},
{"learn":[5.206364257],"iteration":112,"passed_time":0.2586878763,"remaining_time":2.030585366},
{"learn":[5.196937641],"iteration":113,"passed_time":0.2602482939,"remaining_time":2.022631477},
{"learn":[5.190746047],"iteration":114,"passed_time":0.2616917342,"remaining_time":2.013888563},
{"learn":[5.181885213],"iteration":115,"passed_time":0.265347432,"remaining_time":2.02213043},
{"learn":[5.178293568],"iteration":116,"passed_time":0.2666296427,"remaining_time":2.012256192},
{"learn":[5.170991438],"iteration":117,"passed_time":0.2681901882,"remaining_time":2.004608017},
{"learn":[5.166257212],"iteration":118,"passed_time":0.2696279858,"remaining_time":1.996153408},
{"learn":[5.161421246],"iteration":119,"passed_time":0.2710703918,"remaining_time":1.98784954},
{"learn":[5.158223542],"iteration":120,"passed_time":0.2726005951,"remaining_time":1.980296885},
{"learn":[5.15470988],"iteration":121,"passed_time":0.2737911834,"remaining_time":1.970398845},
{"learn":[5.146388143],"iteration":122,"passed_time":0.2753684483,"remaining_time":1.963399424},
{"learn":[5.139529364],"iteration":123,"passed_time":0.2772569426,"remaining_time":1.958686143},
{"learn":[5.134276023],"iteration":124,"passed_time":0.2803071334,"remaining_time":1.962149934},
{"learn":[5.128536065],"iteration":125,"passed_time":0.2817849221,"remaining_time":1.954603349},
{"learn":[5.123300353],"iteration":126,"passed_time":0.2829451194,"remaining_time":1.944969206},
{"learn":[5.116200518],"iteration":127,"passed_time":0.2847150436,"remaining_time":1.939621235},
{"learn":[5.108728704],"iteration":128,"passed_time":0.2865133374,"remaining_time":1.934520286},
{"learn":[5.104075866],"iteration":129,"passed_time":0.2884021307,"remaining_time":1.930075798},
{"learn":[5.100317606],"iteration":130,"passed_time":0.2902297736,"remaining_time":1.925264682},
{"learn":[5.095814182],"iteration":131,"passed_time":0.2943080454,"remaining_time":1.935298359},
{"learn":[5.092146915],"iteration":132,"passed_time":0.2961594352,"remaining_time":1.930603235},
{"learn":[5.085258329],"iteration":133,"passed_time":0.297797634,"remaining_time":1.924572769},
{"learn":[5.079219421],"iteration":134,"passed_time":0.2992302521,"remaining_time":1.917290134},
{"learn":[5.076476829],"iteration":135,"passed_time":0.3006614324,"remaining_time":1.910084394},
{"learn":[5.072133867],"iteration":136,"passed_time":0.302669179,"remaining_time":1.906594901},
{"learn":[5.067031564],"iteration":137,"passed_time":0.3044694059,"remaining_time":1.901830637},
{"learn":[5.061358312],"iteration":138,"passed_time":0.3062207214,"remaining_time":1.896806052},
{"learn":[5.056759124],"iteration":139,"passed_time":0.3090155738,"remaining_time":1.898238525},
{"learn":[5.050254],"iteration":140,"passed_time":0.3108563781,"remaining_time":1.893798786},
{"learn":[5.048376474],"iteration":141,"passed_time":0.3119841516,"remaining_time":1.885087339},
{"learn":[5.042603751],"iteration":142,"passed_time":0.313547727,"remaining_time":1.879093721},
{"learn":[5.037477349],"iteration":143,"passed_time":0.3150195226,"remaining_time":1.872616051},
{"learn":[5.03230489],"iteration":144,"passed_time":0.3167329141,"remaining_time":1.867632011},
{"learn":[5.025976187],"iteration":145,"passed_time":0.3182360484,"remaining_time":1.861462913},
{"learn":[5.01952451],"iteration":146,"passed_time":0.3197431753,"remaining_time":1.855380466},
{"learn":[5.017569424],"iteration":147,"passed_time":0.3212879467,"remaining_time":1.849576558},
{"learn":[5.008962367],"iteration":148,"passed_time":0.3240974319,"remaining_time":1.851053118},
{"learn":[5.003880266],"iteration":149,"passed_time":0.3268543787,"remaining_time":1.852174812},
{"learn":[4.996387564],"iteration":150,"passed_time":0.3296808031,"remaining_time":1.853635773},
{"learn":[4.993361683],"iteration":151,"passed_time":0.3310215167,"remaining_time":1.846751619},
{"learn":[4.99005752],"iteration":152,"passed_time":0.3324252354,"remaining_time":1.840288722},
{"learn":[4.986908764],"iteration":153,"passed_time":0.3346672994,"remaining_time":1.838496983},
{"learn":[4.985207175],"iteration":154,"passed_time":0.3369475992,"remaining_time":1.836907879},
{"learn":[4.979003494],"iteration":155,"passed_time":0.3389071411,"remaining_time":1.833574533},
{"learn":[4.973142217],"iteration":156,"passed_time":0.3408632135,"remaining_time":1.830240057},
{"learn":[4.967056696],"iteration":157,"passed_time":0.3431882534,"remaining_time":1.8288893},
{"learn":[4.961460696],"iteration":158,"passed_time":0.3451608818,"remaining_time":1.825662274},
{"learn":[4.954240363],"iteration":159,"passed_time":0.3467838799,"remaining_time":1.820615369},
{"learn":[4.952320707],"iteration":160,"passed_time":0.3478473233,"remaining_time":1.812695058},
{"learn":[4.948337777],"iteration":161,"passed_time":0.3493482507,"remaining_time":1.807122433},
{"learn":[4.943228639],"iteration":162,"passed_time":0.3507167603,"remaining_time":1.800919806},
{"learn":[4.938545759],"iteration":163,"passed_time":0.3541949151,"remaining_time":1.805530177},
{"learn":[4.935330572],"iteration":164,"passed_time":0.3557141926,"remaining_time":1.800129399},
{"learn":[4.932051543],"iteration":165,"passed_time":0.3572125046,"remaining_time":1.794670053},
{"learn":[4.928964153],"iteration":166,"passed_time":0.3586604185,"remaining_time":1.789006758},
{"learn":[4.922860227],"iteration":167,"passed_time":0.3601253971,"remaining_time":1.783478157},
{"learn":[4.917668772],"iteration":168,"passed_time":0.3616326445,"remaining_time":1.778205488},
{"learn":[4.910365386],"iteration":169,"passed_time":0.3630743125,"remaining_time":1.772656938},
{"learn":[4.906457206],"iteration":170,"passed_time":0.3645772421,"remaining_time":1.767453414},
{"learn":[4.901996508],"iteration":171,"passed_time":0.3670826687,"remaining_time":1.767118893},
{"learn":[4.896816173],"iteration":172,"passed_time":0.3693808872,"remaining_time":1.76576875},
{"learn":[4.891123132],"iteration":173,"passed_time":0.3711634523,"remaining_time":1.761959837},
{"learn":[4.887630202],"iteration":174,"passed_time":0.3726715394,"remaining_time":1.756880114},
{"learn":[4.885259712],"iteration":175,"passed_time":0.3741563312,"remaining_time":1.751731914},
{"learn":[4.880659728],"iteration":176,"passed_time":0.3759114659,"remaining_time":1.747882127},
{"learn":[4.877299723],"iteration":177,"passed_time":0.3776604626,"remaining_time":1.744027529},
{"learn":[4.874038772],"iteration":178,"passed_time":0.3791638453,"remaining_time":1.739069928},
{"learn":[4.86943698],"iteration":179,"passed_time":0.3805406055,"remaining_time":1.733573869},
{"learn":[4.861268711],"iteration":180,"passed_time":0.3845109348,"remaining_time":1.739858871},
{"learn":[4.858673056],"iteration":181,"passed_time":0.386348812,"remaining_time":1.736446858},
{"learn":[4.854036207],"iteration":182,"passed_time":0.3878823366,"remaining_time":1.731693273},
{"learn":[4.85130244],"iteration":183,"passed_time":0.3896002758,"remaining_time":1.727792528},
{"learn":[4.847510084],"iteration":184,"passed_time":0.3916819079,"remaining_time":1.725517594},
{"learn":[4.845691673],"iteration":185,"passed_time":0.3931184572,"remaining_time":1.720421635},
{"learn":[4.842058646],"iteration":186,"passed_time":0.3945723348,"remaining_time":1.715440151},
{"learn":[4.838623675],"iteration":187,"passed_time":0.3979726283,"remaining_time":1.718903054},
{"learn":[4.834602161],"iteration":188,"passed_time":0.4001226935,"remaining_time":1.716928595},
{"learn":[4.830858976],"iteration":189,"passed_time":0.4019218102,"remaining_time":1.713456138},
{"learn":[4.827590511],"iteration":190,"passed_time":0.4035086296,"remaining_time":1.709101997},
{"learn":[4.822246226],"iteration":191,"passed_time":0.4049830785,"remaining_time":1.704303789},
{"learn":[4.816686395],"iteration":192,"passed_time":0.4063759936,"remaining_time":1.699199103},
{"learn":[4.814797121],"iteration":193,"passed_time":0.4090900407,"remaining_time":1.699621509},
{"learn":[4.811639392],"iteration":194,"passed_time":0.4111617173,"remaining_time":1.69735991},
{"learn":[4.804813432],"iteration":195,"passed_time":0.4143988128,"remaining_time":1.699880844},
{"learn":[4.80251613],"iteration":196,"passed_time":0.4162433427,"remaining_time":1.696667026},
{"learn":[4.800087884],"iteration":197,"passed_time":0.4178643091,"remaining_time":1.692561495},
{"learn":[4.794773135],"iteration":198,"passed_time":0.4194123402,"remaining_time":1.688187359},
{"learn":[4.791664833],"iteration":199,"passed_time":0.4210388669,"remaining_time":1.684155468},
{"learn":[4.785989873],"iteration":200,"passed_time":0.4226268681,"remaining_time":1.679994366},
{"learn":[4.782387142],"iteration":201,"passed_time":0.4247056404,"remaining_time":1.67779753},
{"learn":[4.778623704],"iteration":202,"passed_time":0.4284399728,"remaining_time":1.682101765},
{"learn":[4.775772178],"iteration":203,"passed_time":0.4305250466,"remaining_time":1.679891848},
{"learn":[4.77023101],"iteration":204,"passed_time":0.432591083,"remaining_time":1.677609322},
{"learn":[4.764496689],"iteration":205,"passed_time":0.4344556653,"remaining_time":1.674552419},
{"learn":[4.763138716],"iteration":206,"passed_time":0.4362323795,"remaining_time":1.67117042},
{"learn":[4.758053283],"iteration":207,"passed_time":0.4377458155,"remaining_time":1.666801374},
{"learn":[4.755063788],"iteration":208,"passed_time":0.4392091338,"remaining_time":1.662269975},
{"learn":[4.752465267],"iteration":209,"passed_time":0.440798524,"remaining_time":1.658242067},
{"learn":[4.748067377],"iteration":210,"passed_time":0.4442463324,"remaining_time":1.661186522},
{"learn":[4.744163298],"iteration":211,"passed_time":0.4464103321,"remaining_time":1.659298782},
{"learn":[4.736670896],"iteration":212,"passed_time":0.4480922375,"remaining_time":1.655627187},
{"learn":[4.73349255],"iteration":213,"passed_time":0.449553563,"remaining_time":1.651164021},
{"learn":[4.731864595],"iteration":214,"passed_time":0.4512898186,"remaining_time":1.647732593},
{"learn":[4.728398311],"iteration":215,"passed_time":0.4529880246,"remaining_time":1.644178756},
{"learn":[4.723865975],"iteration":216,"passed_time":0.4544346835,"remaining_time":1.639734365},
{"learn":[4.723483365],"iteration":217,"passed_time":0.4579122984,"remaining_time":1.642602832},
{"learn":[4.72095416],"iteration":218,"passed_time":0.4601102288,"remaining_time":1.64084972},
{"learn":[4.716173382],"iteration":219,"passed_time":0.4616587611,"remaining_time":1.636790153},
{"learn":[4.710563974],"iteration":220,"passed_time":0.4633090093,"remaining_time":1.633111847},
{"learn":[4.707160263],"iteration":221,"passed_time":0.4650404493,"remaining_time":1.629736349},
{"learn":[4.70408351],"iteration":222,"passed_time":0.4667580997,"remaining_time":1.626327549},
{"learn":[4.702501831],"iteration":223,"passed_time":0.4683864946,"remaining_time":1.622624642},
{"learn":[4.700269738],"iteration":224,"passed_time":0.4717973012,"remaining_time":1.625079593},
{"learn":[4.695346302],"iteration":225,"passed_time":0.4744606909,"remaining_time":1.624922897},
{"learn":[4.689769299],"iteration":226,"passed_time":0.4764819745,"remaining_time":1.622557561},
{"learn":[4.687919514],"iteration":227,"passed_time":0.4783195476,"remaining_time":1.619573205},
{"learn":[4.682982074],"iteration":228,"passed_time":0.4800149151,"remaining_time":1.616120085},
{"learn":[4.679578702],"iteration":229,"passed_time":0.481926447,"remaining_time":1.613405931},
{"learn":[4.675751423],"iteration":230,"passed_time":0.4834722484,"remaining_time":1.609481208},
{"learn":[4.672710726],"iteration":231,"passed_time":0.4884358504,"remaining_time":1.616891091},
{"learn":[4.6690533],"iteration":232,"passed_time":0.4900721977,"remaining_time":1.613241956},
{"learn":[4.667595702],"iteration":233,"passed_time":0.491620714,"remaining_time":1.609322508},
{"learn":[4.664241291],"iteration":234,"passed_time":0.4931392553,"remaining_time":1.605325661},
{"learn":[4.662246999],"iteration":235,"passed_time":0.4947849668,"remaining_time":1.601761503},
{"learn":[4.658668443],"iteration":236,"passed_time":0.4964573707,"remaining_time":1.598299468},
{"learn":[4.658017572],"iteration":237,"passed_time":0.4981856074,"remaining_time":1.59503123},
{"learn":[4.657656705],"iteration":238,"passed_time":0.4998793635,"remaining_time":1.59166609},
{"learn":[4.653242871],"iteration":239,"passed_time":0.5030154699,"remaining_time":1.592882321},
{"learn":[4.6507302],"iteration":240,"passed_time":0.5045265482,"remaining_time":1.588944606},
{"learn":[4.647671336],"iteration":241,"passed_time":0.5068456993,"remaining_time":1.587558017},
{"learn":[4.645506007],"iteration":242,"passed_time":0.5086799099,"remaining_time":1.584653053},
{"learn":[4.641297906],"iteration":243,"passed_time":0.5101328331,"remaining_time":1.580575499},
{"learn":[4.63798107],"iteration":244,"passed_time":0.5118920379,"remaining_time":1.577463219},
{"learn":[4.635062318],"iteration":245,"passed_time":0.5134828744,"remaining_time":1.573845883},
{"learn":[4.631606017],"iteration":246,"passed_time":0.5149974138,"remaining_time":1.570012359},
{"learn":[4.630215494],"iteration":247,"passed_time":0.5176097542,"remaining_time":1.569526352},
{"learn":[4.62729814],"iteration":248,"passed_time":0.5222509888,"remaining_time":1.57514254},
{"learn":[4.624691756],"iteration":249,"passed_time":0.5238531393,"remaining_time":1.571559418},
{"learn":[4.621840053],"iteration":250,"passed_time":0.5254646759,"remaining_time":1.568020089},
{"learn":[4.619602091],"iteration":251,"passed_time":0.5275560268,"remaining_time":1.56592027},
{"learn":[4.613584029],"iteration":252,"passed_time":0.5295500418,"remaining_time":1.563533127},
{"learn":[4.6119388],"iteration":253,"passed_time":0.5357209657,"remaining_time":1.573416695},
{"learn":[4.60870702],"iteration":254,"passed_time":0.5374329261,"remaining_time":1.570147176},
{"learn":[4.604771557],"iteration":255,"passed_time":0.539190843,"remaining_time":1.567023388},
{"learn":[4.604231277],"iteration":256,"passed_time":0.5408688392,"remaining_time":1.563679173},
{"learn":[4.600750354],"iteration":257,"passed_time":0.5423724965,"remaining_time":1.559846482},
{"learn":[4.596488253],"iteration":258,"passed_time":0.5440953423,"remaining_time":1.556658875},
{"learn":[4.59470784],"iteration":259,"passed_time":0.548164955,"remaining_time":1.560161795},
{"learn":[4.588818005],"iteration":260,"passed_time":0.5508040309,"remaining_time":1.559556241},
{"learn":[4.585054174],"iteration":261,"passed_time":0.5540704814,"remaining_time":1.560702348},
{"learn":[4.581471435],"iteration":262,"passed_time":0.555695026,"remaining_time":1.557213818},
{"learn":[4.577555199],"iteration":263,"passed_time":0.5573181985,"remaining_time":1.553735584},
{"learn":[4.57457145],"iteration":264,"passed_time":0.5589979475,"remaining_time":1.55042827},
{"learn":[4.573029224],"iteration":265,"passed_time":0.5605487373,"remaining_time":1.546777343},
{"learn":[4.571326203],"iteration":266,"passed_time":0.564803836,"remaining_time":1.550566336},
{"learn":[4.571019224],"iteration":267,"passed_time":0.5669893766,"remaining_time":1.548642626},
{"learn":[4.565766631],"iteration":268,"passed_time":0.5687447875,"remaining_time":1.545548103},
{"learn":[4.563383471],"iteration":269,"passed_time":0.5703676905,"remaining_time":1.542105237},
{"learn":[4.558165805],"iteration":270,"passed_time":0.5721050167,"remaining_time":1.538983606},
{"learn":[4.55629209],"iteration":271,"passed_time":0.5738367971,"remaining_time":1.53585731},
{"learn":[4.549383848],"iteration":272,"passed_time":0.5802355265,"remaining_time":1.545169332},
{"learn":[4.546227503],"iteration":273,"passed_time":0.5828823804,"remaining_time":1.544425577},
{"learn":[4.540620977],"iteration":274,"passed_time":0.5848266586,"remaining_time":1.541815736},
{"learn":[4.532898237],"iteration":275,"passed_time":0.5938268978,"remaining_time":1.557719833},
{"learn":[4.529757367],"iteration":276,"passed_time":0.5966792961,"remaining_time":1.557397585},
{"learn":[4.52579294],"iteration":277,"passed_time":0.5989251464,"remaining_time":1.555481855},
{"learn":[4.521572155],"iteration":278,"passed_time":0.6009562111,"remaining_time":1.553008703},
{"learn":[4.518818099],"iteration":279,"passed_time":0.6109315009,"remaining_time":1.570966717},
{"learn":[4.514012334],"iteration":280,"passed_time":0.613589674,"remaining_time":1.570003472},
{"learn":[4.508331416],"iteration":281,"passed_time":0.6155767946,"remaining_time":1.56731964},
{"learn":[4.506038537],"iteration":282,"passed_time":0.6243041244,"remaining_time":1.581717517},
{"learn":[4.505805643],"iteration":283,"passed_time":0.6300238319,"remaining_time":1.588369942},
{"learn":[4.501550352],"iteration":284,"passed_time":0.6357027052,"remaining_time":1.594833103},
{"learn":[4.494692643],"iteration":285,"passed_time":0.641413378,"remaining_time":1.601290741},
{"learn":[4.489330245],"iteration":286,"passed_time":0.6440952112,"remaining_time":1.600138974},
{"learn":[4.484826955],"iteration":287,"passed_time":0.6463202788,"remaining_time":1.597847356},
{"learn":[4.478285428],"iteration":288,"passed_time":0.6539588279,"remaining_time":1.608874487},
{"learn":[4.475311671],"iteration":289,"passed_time":0.6556400662,"remaining_time":1.605187748},
{"learn":[4.471581298],"iteration":290,"passed_time":0.6576175876,"remaining_time":1.602236665},
{"learn":[4.469164956],"iteration":291,"passed_time":0.6594344934,"remaining_time":1.598902813},
{"learn":[4.462068024],"iteration":292,"passed_time":0.6616835589,"remaining_time":1.596622103},
{"learn":[4.458540976],"iteration":293,"passed_time":0.6631088344,"remaining_time":1.592363392},
{"learn":[4.455757458],"iteration":294,"passed_time":0.6676538947,"remaining_time":1.595579647},
{"learn":[4.453027414],"iteration":295,"passed_time":0.6693902185,"remaining_time":1.592063222},
{"learn":[4.450659338],"iteration":296,"passed_time":0.6710094312,"remaining_time":1.588281583},
{"learn":[4.444696901],"iteration":297,"passed_time":0.6726985941,"remaining_time":1.584679238},
{"learn":[4.442052813],"iteration":298,"passed_time":0.6744033888,"remaining_time":1.58112634},
{"learn":[4.440036756],"iteration":299,"passed_time":0.6759865121,"remaining_time":1.577301862},
{"learn":[4.435017051],"iteration":300,"passed_time":0.6777357076,"remaining_time":1.573877939},
{"learn":[4.429962125],"iteration":301,"passed_time":0.67929752,"remaining_time":1.570032016},
{"learn":[4.427666256],"iteration":302,"passed_time":0.6823677085,"remaining_time":1.569670933},
{"learn":[4.425030004],"iteration":303,"passed_time":0.6842095497,"remaining_time":1.566479758},
{"learn":[4.422588771],"iteration":304,"passed_time":0.6873170903,"remaining_time":1.566181566},
{"learn":[4.418936667],"iteration":305,"passed_time":0.69155659,"remaining_time":1.568432266},
{"learn":[4.416887976],"iteration":306,"passed_time":0.6932187925,"remaining_time":1.564822877},
{"learn":[4.413773354],"iteration":307,"passed_time":0.6969719677,"remaining_time":1.565924031},
{"learn":[4.411129391],"iteration":308,"passed_time":0.6989879497,"remaining_time":1.563108975},
{"learn":[4.40850819],"iteration":309,"passed_time":0.7004023837,"remaining_time":1.558960144},
{"learn":[4.404880292],"iteration":310,"passed_time":0.702036359,"remaining_time":1.555315278},
{"learn":[4.404593827],"iteration":311,"passed_time":0.7037759452,"remaining_time":1.551916187},
{"learn":[4.402139942],"iteration":312,"passed_time":0.7053116598,"remaining_time":1.548080225},
{"learn":[4.400284725],"iteration":313,"passed_time":0.7068985255,"remaining_time":1.544370664},
{"learn":[4.395805521],"iteration":314,"passed_time":0.7083345694,"remaining_time":1.540346603},
{"learn":[4.392838833],"iteration":315,"passed_time":0.7106955337,"remaining_time":1.538340965},
{"learn":[4.389213061],"iteration":316,"passed_time":0.7125707748,"remaining_time":1.535286559},
{"learn":[4.3861981],"iteration":317,"passed_time":0.71451103,"remaining_time":1.532379001},
{"learn":[4.385054234],"iteration":318,"passed_time":0.7162142597,"remaining_time":1.528971507},
{"learn":[4.379364607],"iteration":319,"passed_time":0.7177639232,"remaining_time":1.525248337},
{"learn":[4.378387619],"iteration":320,"passed_time":0.7196405095,"remaining_time":1.522230237},
{"learn":[4.375816727],"iteration":321,"passed_time":0.721369303,"remaining_time":1.518908036},
{"learn":[4.374600202],"iteration":322,"passed_time":0.7228606144,"remaining_time":1.515097944},
{"learn":[4.37098897],"iteration":323,"passed_time":0.7249087413,"remaining_time":1.512463917},
{"learn":[4.367418484],"iteration":324,"passed_time":0.7270938152,"remaining_time":1.510117924},
{"learn":[4.363584638],"iteration":325,"passed_time":0.7287126312,"remaining_time":1.506602188},
{"learn":[4.360770706],"iteration":326,"passed_time":0.7303491579,"remaining_time":1.503134505},
{"learn":[4.358675808],"iteration":327,"passed_time":0.7318606675,"remaining_time":1.499421855},
{"learn":[4.354228195],"iteration":328,"passed_time":0.7334240112,"remaining_time":1.495828303},
{"learn":[4.353773425],"iteration":329,"passed_time":0.7348784692,"remaining_time":1.492025983},
{"learn":[4.351648009],"iteration":330,"passed_time":0.7363803821,"remaining_time":1.488333763},
{"learn":[4.348209927],"iteration":331,"passed_time":0.7378128949,"remaining_time":1.484515102},
{"learn":[4.345852733],"iteration":332,"passed_time":0.7399928029,"remaining_time":1.482207806},
{"learn":[4.34237339],"iteration":333,"passed_time":0.7419688426,"remaining_time":1.479494758},
{"learn":[4.340814362],"iteration":334,"passed_time":0.7435787704,"remaining_time":1.47605935},
{"learn":[4.339707068],"iteration":335,"passed_time":0.7451804535,"remaining_time":1.472618515},
{"learn":[4.335430786],"iteration":336,"passed_time":0.7467583687,"remaining_time":1.469141835},
{"learn":[4.33521887],"iteration":337,"passed_time":0.7481454296,"remaining_time":1.465302587},
{"learn":[4.328507238],"iteration":338,"passed_time":0.7495859748,"remaining_time":1.461582092},
{"learn":[4.326140732],"iteration":339,"passed_time":0.7511234946,"remaining_time":1.458063254},
{"learn":[4.323785636],"iteration":340,"passed_time":0.7525581595,"remaining_time":1.454357264},
{"learn":[4.320632534],"iteration":341,"passed_time":0.7551731356,"remaining_time":1.452935448},
{"learn":[4.31973724],"iteration":342,"passed_time":0.7571618768,"remaining_time":1.450307152},
{"learn":[4.318000924],"iteration":343,"passed_time":0.7588529636,"remaining_time":1.447114954},
{"learn":[4.312713628],"iteration":344,"passed_time":0.7603936706,"remaining_time":1.443645954},
{"learn":[4.308220789],"iteration":345,"passed_time":0.7621055325,"remaining_time":1.440511613},
{"learn":[4.305890947],"iteration":346,"passed_time":0.7636550267,"remaining_time":1.437079921},
{"learn":[4.305137856],"iteration":347,"passed_time":0.7651532991,"remaining_time":1.433563078},
{"learn":[4.304787172],"iteration":348,"passed_time":0.766597784,"remaining_time":1.429957471},
{"learn":[4.30350134],"iteration":349,"passed_time":0.7680471618,"remaining_time":1.426373301},
{"learn":[4.30293809],"iteration":350,"passed_time":0.7714224956,"remaining_time":1.426362392},
{"learn":[4.299548459],"iteration":351,"passed_time":0.7732585071,"remaining_time":1.423498615},
{"learn":[4.294768408],"iteration":352,"passed_time":0.774878814,"remaining_time":1.420245305},
{"learn":[4.294581479],"iteration":353,"passed_time":0.7771008896,"remaining_time":1.418099364},
{"learn":[4.292551604],"iteration":354,"passed_time":0.7788917625,"remaining_time":1.41516954},
{"learn":[4.288628894],"iteration":355,"passed_time":0.7807514652,"remaining_time":1.412370628},
{"learn":[4.287802767],"iteration":356,"passed_time":0.7823056714,"remaining_time":1.409026742},
{"learn":[4.284566905],"iteration":357,"passed_time":0.7863270247,"remaining_time":1.410117178},
{"learn":[4.27890232],"iteration":358,"passed_time":0.7882799493,"remaining_time":1.407485926},
{"learn":[4.276938023],"iteration":359,"passed_time":0.790824293,"remaining_time":1.405909854},
{"learn":[4.273425094],"iteration":360,"passed_time":0.7927900008,"remaining_time":1.403304184},
{"learn":[4.269726505],"iteration":361,"passed_time":0.7945941926,"remaining_time":1.400417389},
{"learn":[4.265565857],"iteration":362,"passed_time":0.7963794202,"remaining_time":1.39750328},
{"learn":[4.262117173],"iteration":363,"passed_time":0.798543959,"remaining_time":1.395258126},
{"learn":[4.259185148],"iteration":364,"passed_time":0.8031345301,"remaining_time":1.397234046},
{"learn":[4.257668507],"iteration":365,"passed_time":0.8050573981,"remaining_time":1.394552979},
{"learn":[4.253432436],"iteration":366,"passed_time":0.8069662236,"remaining_time":1.391851824},
{"learn":[4.250216667],"iteration":367,"passed_time":0.808848312,"remaining_time":1.389109057},
{"learn":[4.24514828],"iteration":368,"passed_time":0.8105614424,"remaining_time":1.386082033},
{"learn":[4.244015772],"iteration":369,"passed_time":0.8120779511,"remaining_time":1.382727322},
{"learn":[4.240329192],"iteration":370,"passed_time":0.8139091436,"remaining_time":1.379916041},
{"learn":[4.236718014],"iteration":371,"passed_time":0.8177114458,"remaining_time":1.380437602},
{"learn":[4.233495944],"iteration":372,"passed_time":0.8193194362,"remaining_time":1.377247417},
{"learn":[4.230357491],"iteration":373,"passed_time":0.8212626749,"remaining_time":1.37462683},
{"learn":[4.227381215],"iteration":374,"passed_time":0.8232649952,"remaining_time":1.372108325},
{"learn":[4.226169067],"iteration":375,"passed_time":0.8249747732,"remaining_time":1.36910707},
{"learn":[4.225963861],"iteration":376,"passed_time":0.8268571134,"remaining_time":1.366397829},
{"learn":[4.224346548],"iteration":377,"passed_time":0.8284406393,"remaining_time":1.363201264},
{"learn":[4.222595381],"iteration":378,"passed_time":0.8324810696,"remaining_time":1.364038903},
{"learn":[4.219700938],"iteration":379,"passed_time":0.8342853211,"remaining_time":1.361202366},
{"learn":[4.216356207],"iteration":380,"passed_time":0.8359555232,"remaining_time":1.358153462},
{"learn":[4.214326494],"iteration":381,"passed_time":0.8375694857,"remaining_time":1.355020791},
{"learn":[4.212901398],"iteration":382,"passed_time":0.8394956126,"remaining_time":1.352398937},
{"learn":[4.211331091],"iteration":383,"passed_time":0.8411647113,"remaining_time":1.349368391},
{"learn":[4.208624791],"iteration":384,"passed_time":0.8427290456,"remaining_time":1.346177566},
{"learn":[4.204659106],"iteration":385,"passed_time":0.8447215334,"remaining_time":1.343676222},
{"learn":[4.202968852],"iteration":386,"passed_time":0.8470185399,"remaining_time":1.341659858},
{"learn":[4.197261935],"iteration":387,"passed_time":0.8485392906,"remaining_time":1.338417644},
{"learn":[4.196934403],"iteration":388,"passed_time":0.8501468413,"remaining_time":1.335320617},
{"learn":[4.192479929],"iteration":389,"passed_time":0.8518827558,"remaining_time":1.332432003},
{"learn":[4.190243116],"iteration":390,"passed_time":0.8533504475,"remaining_time":1.329131515},
{"learn":[4.185852431],"iteration":391,"passed_time":0.8549671703,"remaining_time":1.32607153},
{"learn":[4.180967944],"iteration":392,"passed_time":0.8566937577,"remaining_time":1.323188577},
{"learn":[4.178283162],"iteration":393,"passed_time":0.8584370114,"remaining_time":1.320337129},
{"learn":[4.176341157],"iteration":394,"passed_time":0.8610743294,"remaining_time":1.318860682},
{"learn":[4.176041504],"iteration":395,"passed_time":0.8632781392,"remaining_time":1.316717162},
{"learn":[4.175564513],"iteration":396,"passed_time":0.8649941293,"remaining_time":1.313832393},
{"learn":[4.170830274],"iteration":397,"passed_time":0.8666523569,"remaining_time":1.310866128},
{"learn":[4.167804808],"iteration":398,"passed_time":0.8682074837,"remaining_time":1.307751122},
{"learn":[4.165860548],"iteration":399,"passed_time":0.8699462529,"remaining_time":1.304919379},
{"learn":[4.160950571],"iteration":400,"passed_time":0.8714762127,"remaining_time":1.301781176},
{"learn":[4.158544115],"iteration":401,"passed_time":0.8729623396,"remaining_time":1.298585769},
{"learn":[4.154448767],"iteration":402,"passed_time":0.8759300221,"remaining_time":1.297593606},
{"learn":[4.15197457],"iteration":403,"passed_time":0.8775857918,"remaining_time":1.294656267},
{"learn":[4.149562679],"iteration":404,"passed_time":0.8790676657,"remaining_time":1.291469781},
{"learn":[4.149327961],"iteration":405,"passed_time":0.8805198435,"remaining_time":1.288248244},
{"learn":[4.147444889],"iteration":406,"passed_time":0.8820903369,"remaining_time":1.285207788},
{"learn":[4.147254809],"iteration":407,"passed_time":0.8839530165,"remaining_time":1.282598494},
{"learn":[4.144589165],"iteration":408,"passed_time":0.8855195038,"remaining_time":1.279564858},
{"learn":[4.141691034],"iteration":409,"passed_time":0.8869117147,"remaining_time":1.276287589},
{"learn":[4.138893468],"iteration":410,"passed_time":0.8891416248,"remaining_time":1.274219993},
{"learn":[4.136964597],"iteration":411,"passed_time":0.8913968367,"remaining_time":1.272187718},
{"learn":[4.133773523],"iteration":412,"passed_time":0.8932623767,"remaining_time":1.269600521},
{"learn":[4.131363444],"iteration":413,"passed_time":0.8953807106,"remaining_time":1.267374629},
{"learn":[4.130228592],"iteration":414,"passed_time":0.8968691168,"remaining_time":1.264261285},
{"learn":[4.12884186],"iteration":415,"passed_time":0.8985153935,"remaining_time":1.261377379},
{"learn":[4.12413494],"iteration":416,"passed_time":0.9000879372,"remaining_time":1.258396325},
{"learn":[4.119422508],"iteration":417,"passed_time":0.9020205154,"remaining_time":1.255923301},
{"learn":[4.117038244],"iteration":418,"passed_time":0.9048064905,"remaining_time":1.254636208},
{"learn":[4.116067631],"iteration":419,"passed_time":0.9068158535,"remaining_time":1.252269512},
{"learn":[4.110343455],"iteration":420,"passed_time":0.9085003633,"remaining_time":1.249457744},
{"learn":[4.105604544],"iteration":421,"passed_time":0.9105411653,"remaining_time":1.247139321},
{"learn":[4.103390131],"iteration":422,"passed_time":0.9121391447,"remaining_time":1.244218171},
{"learn":[4.096724402],"iteration":423,"passed_time":0.9138516273,"remaining_time":1.241458815},
{"learn":[4.093431279],"iteration":424,"passed_time":0.9153771734,"remaining_time":1.23845147},
{"learn":[4.091412744],"iteration":425,"passed_time":0.9169042272,"remaining_time":1.235453114},
{"learn":[4.091192901],"iteration":426,"passed_time":0.9206240918,"remaining_time":1.235404226},
{"learn":[4.088994581],"iteration":427,"passed_time":0.9226049749,"remaining_time":1.233014125},
{"learn":[4.087845355],"iteration":428,"passed_time":0.9244420536,"remaining_time":1.230434528},
{"learn":[4.083650279],"iteration":429,"passed_time":0.926076552,"remaining_time":1.227589848},
{"learn":[4.079840652],"iteration":430,"passed_time":0.9278969973,"remaining_time":1.224996268},
{"learn":[4.075707828],"iteration":431,"passed_time":0.9293712263,"remaining_time":1.221951057},
{"learn":[4.071345409],"iteration":432,"passed_time":0.930935308,"remaining_time":1.219030761},
{"learn":[4.067460475],"iteration":433,"passed_time":0.9359365021,"remaining_time":1.220599217},
{"learn":[4.064914749],"iteration":434,"passed_time":0.9384462329,"remaining_time":1.218901429},
{"learn":[4.063823175],"iteration":435,"passed_time":0.940146159,"remaining_time":1.216152371},
{"learn":[4.058898471],"iteration":436,"passed_time":0.9417701873,"remaining_time":1.213310333},
{"learn":[4.054120355],"iteration":437,"passed_time":0.9433979412,"remaining_time":1.210478637},
{"learn":[4.052715901],"iteration":438,"passed_time":0.9450359193,"remaining_time":1.207665491},
{"learn":[4.052114167],"iteration":439,"passed_time":0.9466104702,"remaining_time":1.204776962},
{"learn":[4.051377267],"iteration":440,"passed_time":0.9489972332,"remaining_time":1.202923931},
{"learn":[4.049275336],"iteration":441,"passed_time":0.9533650369,"remaining_time":1.203569436},
{"learn":[4.047099198],"iteration":442,"passed_time":0.9558878979,"remaining_time":1.201872594},
{"learn":[4.044348685],"iteration":443,"passed_time":0.9576540856,"remaining_time":1.199224486},
{"learn":[4.042822379],"iteration":444,"passed_time":0.9593751642,"remaining_time":1.196524081},
{"learn":[4.041258611],"iteration":445,"passed_time":0.9609613038,"remaining_time":1.193660454},
{"learn":[4.040044254],"iteration":446,"passed_time":0.9627175209,"remaining_time":1.191012951},
{"learn":[4.036860137],"iteration":447,"passed_time":0.9672325884,"remaining_time":1.191768725},
{"learn":[4.036372284],"iteration":448,"passed_time":0.9694177777,"remaining_time":1.189641861},
{"learn":[4.03368231],"iteration":449,"passed_time":0.9709205894,"remaining_time":1.18668072},
{"learn":[4.032439519],"iteration":450,"passed_time":0.9724576577,"remaining_time":1.183767747},
{"learn":[4.032008634],"iteration":451,"passed_time":0.9740361557,"remaining_time":1.180911091},
{"learn":[4.030034932],"iteration":452,"passed_time":0.9756600139,"remaining_time":1.178114851},
{"learn":[4.028173412],"iteration":453,"passed_time":0.9780161407,"remaining_time":1.176204433},
{"learn":[4.023806097],"iteration":454,"passed_time":0.981932535,"remaining_time":1.176160949},
{"learn":[4.020239186],"iteration":455,"passed_time":0.984044308,"remaining_time":1.173947596},
{"learn":[4.017384838],"iteration":456,"passed_time":0.9858425934,"remaining_time":1.171362206},
{"learn":[4.016468229],"iteration":457,"passed_time":0.9875836511,"remaining_time":1.16871253},
{"learn":[4.014530169],"iteration":458,"passed_time":0.9892895182,"remaining_time":1.166025336},
{"learn":[4.012884822],"iteration":459,"passed_time":0.9908733271,"remaining_time":1.163199123},
{"learn":[4.008924707],"iteration":460,"passed_time":0.9930514249,"remaining_time":1.161073141},
{"learn":[4.008286778],"iteration":461,"passed_time":0.9987154732,"remaining_time":1.16300633},
{"learn":[4.006444202],"iteration":462,"passed_time":1.000277852,"remaining_time":1.160149474},
{"learn":[4.003284363],"iteration":463,"passed_time":1.001674703,"remaining_time":1.157106984},
{"learn":[3.999811484],"iteration":464,"passed_time":1.002982044,"remaining_time":1.153968589},
{"learn":[3.997483319],"iteration":465,"passed_time":1.004403861,"remaining_time":1.150969231},
{"learn":[3.99708333],"iteration":466,"passed_time":1.005827889,"remaining_time":1.147979154},
{"learn":[3.995860263],"iteration":467,"passed_time":1.00723942,"remaining_time":1.144981563},
{"learn":[3.994131111],"iteration":468,"passed_time":1.008604455,"remaining_time":1.141938093},
{"learn":[3.993125499],"iteration":469,"passed_time":1.011182298,"remaining_time":1.1402694},
{"learn":[3.992954084],"iteration":470,"passed_time":1.013772366,"remaining_time":1.138610576},
{"learn":[3.990635743],"iteration":471,"passed_time":1.015386583,"remaining_time":1.135856178},
{"learn":[3.986678254],"iteration":472,"passed_time":1.017066826,"remaining_time":1.133180163},
{"learn":[3.986393291],"iteration":473,"passed_time":1.018811931,"remaining_time":1.130580329},
{"learn":[3.986152671],"iteration":474,"passed_time":1.02043825,"remaining_time":1.127852802},
{"learn":[3.985596662],"iteration":475,"passed_time":1.022199619,"remaining_time":1.125278572},
{"learn":[3.983853457],"iteration":476,"passed_time":1.027753325,"remaining_time":1.126865805},
{"learn":[3.983263928],"iteration":477,"passed_time":1.029866979,"remaining_time":1.12466645},
{"learn":[3.980067202],"iteration":478,"passed_time":1.032111394,"remaining_time":1.122609679},
{"learn":[3.978115407],"iteration":479,"passed_time":1.034020894,"remaining_time":1.120189301},
{"learn":[3.972661644],"iteration":480,"passed_time":1.035859317,"remaining_time":1.117694356},
{"learn":[3.969938254],"iteration":481,"passed_time":1.038716199,"remaining_time":1.116296662},
{"learn":[3.968211434],"iteration":482,"passed_time":1.042401752,"remaining_time":1.115779929},
{"learn":[3.966113368],"iteration":483,"passed_time":1.044652519,"remaining_time":1.113720454},
{"learn":[3.962246044],"iteration":484,"passed_time":1.046198455,"remaining_time":1.110911762},
{"learn":[3.961319703],"iteration":485,"passed_time":1.048402348,"remaining_time":1.10880413},
{"learn":[3.96078191],"iteration":486,"passed_time":1.050222921,"remaining_time":1.106292317},
{"learn":[3.958913633],"iteration":487,"passed_time":1.051743398,"remaining_time":1.103468483},
{"learn":[3.957428286],"iteration":488,"passed_time":1.059398152,"remaining_time":1.107060237},
{"learn":[3.952641965],"iteration":489,"passed_time":1.063939191,"remaining_time":1.107365281},
{"learn":[3.951486786],"iteration":490,"passed_time":1.065800225,"remaining_time":1.104872331},
{"learn":[3.94938344],"iteration":491,"passed_time":1.07090307,"remaining_time":1.105729186},
{"learn":[3.947297924],"iteration":492,"passed_time":1.073388969,"remaining_time":1.103870603},
{"learn":[3.946284886],"iteration":493,"passed_time":1.075971289,"remaining_time":1.102108243},
{"learn":[3.943288204],"iteration":494,"passed_time":1.077851067,"remaining_time":1.099625836},
{"learn":[3.943076488],"iteration":495,"passed_time":1.079869202,"remaining_time":1.097286447},
{"learn":[3.942347078],"iteration":496,"passed_time":1.082593299,"remaining_time":1.095662836},
{"learn":[3.940251541],"iteration":497,"passed_time":1.087606329,"remaining_time":1.096342123},
{"learn":[3.939011019],"iteration":498,"passed_time":1.089450478,"remaining_time":1.093817013},
{"learn":[3.938760512],"iteration":499,"passed_time":1.091391423,"remaining_time":1.091391423},
{"learn":[3.934522727],"iteration":500,"passed_time":1.094187721,"remaining_time":1.089819706},
{"learn":[3.930091193],"iteration":501,"passed_time":1.09629987,"remaining_time":1.087564413},
{"learn":[3.927671752],"iteration":502,"passed_time":1.10173131,"remaining_time":1.088589386},
{"learn":[3.927280041],"iteration":503,"passed_time":1.103900662,"remaining_time":1.086378429},
{"learn":[3.925987561],"iteration":504,"passed_time":1.106107148,"remaining_time":1.084204036},
{"learn":[3.921645957],"iteration":505,"passed_time":1.107737045,"remaining_time":1.081466602},
{"learn":[3.920333743],"iteration":506,"passed_time":1.110426415,"remaining_time":1.079763753},
{"learn":[3.918659461],"iteration":507,"passed_time":1.113207537,"remaining_time":1.078145882},
{"learn":[3.916124385],"iteration":508,"passed_time":1.116589464,"remaining_time":1.077103},
{"learn":[3.913849268],"iteration":509,"passed_time":1.118740295,"remaining_time":1.074868126},
{"learn":[3.912826119],"iteration":510,"passed_time":1.120665702,"remaining_time":1.072417864},
{"learn":[3.910034145],"iteration":511,"passed_time":1.122911255,"remaining_time":1.07027479},
{"learn":[3.90792379],"iteration":512,"passed_time":1.124504567,"remaining_time":1.067512133},
{"learn":[3.907823851],"iteration":513,"passed_time":1.131668372,"remaining_time":1.070021068},
{"learn":[3.904527401],"iteration":514,"passed_time":1.134489124,"remaining_time":1.068402379},
{"learn":[3.903378283],"iteration":515,"passed_time":1.136165554,"remaining_time":1.065705675},
{"learn":[3.902170135],"iteration":516,"passed_time":1.13790782,"remaining_time":1.063074424},
{"learn":[3.899435429],"iteration":517,"passed_time":1.139538164,"remaining_time":1.060342462},
{"learn":[3.897497505],"iteration":518,"passed_time":1.144624758,"remaining_time":1.060817935},
{"learn":[3.896426119],"iteration":519,"passed_time":1.148543814,"remaining_time":1.06019429},
{"learn":[3.896044669],"iteration":520,"passed_time":1.150373373,"remaining_time":1.05763694},
{"learn":[3.892795942],"iteration":521,"passed_time":1.151841911,"remaining_time":1.054751789},
{"learn":[3.892413888],"iteration":522,"passed_time":1.153608216,"remaining_time":1.052143631},
{"learn":[3.891738985],"iteration":523,"passed_time":1.155312637,"remaining_time":1.049482472},
{"learn":[3.88822057],"iteration":524,"passed_time":1.160266659,"remaining_time":1.049765073},
{"learn":[3.883837053],"iteration":525,"passed_time":1.162988328,"remaining_time":1.048016098},
{"learn":[3.881769742],"iteration":526,"passed_time":1.164901699,"remaining_time":1.045537958},
{"learn":[3.880356898],"iteration":527,"passed_time":1.166747311,"remaining_time":1.043001384},
{"learn":[3.879250273],"iteration":528,"passed_time":1.168598549,"remaining_time":1.040472432},
{"learn":[3.877174493],"iteration":529,"passed_time":1.170726035,"remaining_time":1.038191012},
{"learn":[3.875854201],"iteration":530,"passed_time":1.175214464,"remaining_time":1.03799545},
{"learn":[3.873189396],"iteration":531,"passed_time":1.178210204,"remaining_time":1.03647063},
{"learn":[3.871583368],"iteration":532,"passed_time":1.181133848,"remaining_time":1.034877124},
{"learn":[3.869622679],"iteration":533,"passed_time":1.18636151,"remaining_time":1.035289258},
{"learn":[3.866860164],"iteration":534,"passed_time":1.191609025,"remaining_time":1.035697564},
{"learn":[3.864498444],"iteration":535,"passed_time":1.193972687,"remaining_time":1.033588296},
{"learn":[3.861416322],"iteration":536,"passed_time":1.196233514,"remaining_time":1.031389417},
{"learn":[3.860265769],"iteration":537,"passed_time":1.197970555,"remaining_time":1.028740514},
{"learn":[3.859328725],"iteration":538,"passed_time":1.204090758,"remaining_time":1.029843858},
{"learn":[3.858521278],"iteration":539,"passed_time":1.206236774,"remaining_time":1.02753503},
{"learn":[3.85599111],"iteration":540,"passed_time":1.208321071,"remaining_time":1.025174439},
{"learn":[3.852379816],"iteration":541,"passed_time":1.210964198,"remaining_time":1.02328709},
{"learn":[3.851327537],"iteration":542,"passed_time":1.213004737,"remaining_time":1.020889806},
{"learn":[3.847854898],"iteration":543,"passed_time":1.215047101,"remaining_time":1.018495364},
{"learn":[3.847083414],"iteration":544,"passed_time":1.219200369,"remaining_time":1.017864529},
{"learn":[3.845397429],"iteration":545,"passed_time":1.221013265,"remaining_time":1.015274766},
{"learn":[3.841933528],"iteration":546,"passed_time":1.222707471,"remaining_time":1.012589551},
{"learn":[3.840996474],"iteration":547,"passed_time":1.224922149,"remaining_time":1.010337247},
{"learn":[3.838355966],"iteration":548,"passed_time":1.227329335,"remaining_time":1.008243224},
{"learn":[3.83342799],"iteration":549,"passed_time":1.23197337,"remaining_time":1.007978211},
{"learn":[3.828161535],"iteration":550,"passed_time":1.234164682,"remaining_time":1.005698625},
{"learn":[3.823502399],"iteration":551,"passed_time":1.236267521,"remaining_time":1.003347553},
{"learn":[3.820068862],"iteration":552,"passed_time":1.238096326,"remaining_time":1.000775873},
{"learn":[3.817951642],"iteration":553,"passed_time":1.239761025,"remaining_time":0.99807476},
{"learn":[3.815785958],"iteration":554,"passed_time":1.241779081,"remaining_time":0.9956607049},
{"learn":[3.81503012],"iteration":555,"passed_time":1.247463015,"remaining_time":0.9961755009},
{"learn":[3.813529315],"iteration":556,"passed_time":1.249435891,"remaining_time":0.9937165162},
{"learn":[3.808881326],"iteration":557,"passed_time":1.251711584,"remaining_time":0.9914991404},
{"learn":[3.808740434],"iteration":558,"passed_time":1.253198774,"remaining_time":0.9886594975},
{"learn":[3.80714352],"iteration":559,"passed_time":1.255094175,"remaining_time":0.9861454231},
{"learn":[3.80573346],"iteration":560,"passed_time":1.256795966,"remaining_time":0.9834820482},
{"learn":[3.803370052],"iteration":561,"passed_time":1.258556485,"remaining_time":0.9808678653},
{"learn":[3.803215211],"iteration":562,"passed_time":1.262577513,"remaining_time":0.9800113199},
{"learn":[3.801309667],"iteration":563,"passed_time":1.265120697,"remaining_time":0.9780011059},
{"learn":[3.800003847],"iteration":564,"passed_time":1.26760307,"remaining_time":0.9759421869},
{"learn":[3.798026138],"iteration":565,"passed_time":1.269969964,"remaining_time":0.9737932231},
{"learn":[3.794745847],"iteration":566,"passed_time":1.271923752,"remaining_time":0.971328015},
{"learn":[3.794312041],"iteration":567,"passed_time":1.277863932,"remaining_time":0.9718965119},
{"learn":[3.792205926],"iteration":568,"passed_time":1.280391571,"remaining_time":0.9698572357},
{"learn":[3.788991061],"iteration":569,"passed_time":1.283241742,"remaining_time":0.9680595599},
{"learn":[3.787391572],"iteration":570,"passed_time":1.286409442,"remaining_time":0.966496761},
{"learn":[3.7826445],"iteration":571,"passed_time":1.289014558,"remaining_time":0.9645073969},
{"learn":[3.781700331],"iteration":572,"passed_time":1.294894636,"remaining_time":0.9649563864},
{"learn":[3.780045374],"iteration":573,"passed_time":1.297010705,"remaining_time":0.962589826},
{"learn":[3.775462644],"iteration":574,"passed_time":1.298920881,"remaining_time":0.9600719556},
{"learn":[3.773711943],"iteration":575,"passed_time":1.301253638,"remaining_time":0.9578672616},
{"learn":[3.772415806],"iteration":576,"passed_time":1.303892529,"remaining_time":0.9558865507},
{"learn":[3.770170875],"iteration":577,"passed_time":1.305826096,"remaining_time":0.9533886031},
{"learn":[3.765166479],"iteration":578,"passed_time":1.310189581,"remaining_time":0.9526594364},
{"learn":[3.763976102],"iteration":579,"passed_time":1.312261928,"remaining_time":0.9502586377},
{"learn":[3.760761708],"iteration":580,"passed_time":1.314541049,"remaining_time":0.9480080885},
{"learn":[3.758155662],"iteration":581,"passed_time":1.316596525,"remaining_time":0.9455968169},
{"learn":[3.756844548],"iteration":582,"passed_time":1.318440957,"remaining_time":0.9430358133},
{"learn":[3.753098923],"iteration":583,"passed_time":1.32189987,"remaining_time":0.9416273046},
{"learn":[3.751618946],"iteration":584,"passed_time":1.324298858,"remaining_time":0.9394598733},
{"learn":[3.751398464],"iteration":585,"passed_time":1.327172217,"remaining_time":0.9376267883},
{"learn":[3.749920103],"iteration":586,"passed_time":1.329058302,"remaining_time":0.9350955342},
{"learn":[3.748237465],"iteration":587,"passed_time":1.330934263,"remaining_time":0.9325593815},
{"learn":[3.746021536],"iteration":588,"passed_time":1.332844466,"remaining_time":0.9300493645},
{"learn":[3.74417648],"iteration":589,"passed_time":1.334927242,"remaining_time":0.9276613035},
{"learn":[3.738788389],"iteration":590,"passed_time":1.341177252,"remaining_time":0.9281581994},
{"learn":[3.736021611],"iteration":591,"passed_time":1.344904476,"remaining_time":0.9268936256},
{"learn":[3.734546151],"iteration":592,"passed_time":1.346630539,"remaining_time":0.924247267},
{"learn":[3.733527479],"iteration":593,"passed_time":1.348149999,"remaining_time":0.9214627941},
{"learn":[3.733026392],"iteration":594,"passed_time":1.349696056,"remaining_time":0.9187006767},
{"learn":[3.730314752],"iteration":595,"passed_time":1.354580601,"remaining_time":0.9182056425},
{"learn":[3.727342596],"iteration":596,"passed_time":1.357480695,"remaining_time":0.9163563149},
{"learn":[3.725459604],"iteration":597,"passed_time":1.359221802,"remaining_time":0.9137243553},
{"learn":[3.723158842],"iteration":598,"passed_time":1.360826737,"remaining_time":0.9110042093},
{"learn":[3.722362756],"iteration":599,"passed_time":1.36264607,"remaining_time":0.9084307133},
{"learn":[3.721443615],"iteration":600,"passed_time":1.364907717,"remaining_time":0.9061533764},
{"learn":[3.720743486],"iteration":601,"passed_time":1.369339728,"remaining_time":0.905310983},
{"learn":[3.720215334],"iteration":602,"passed_time":1.371803989,"remaining_time":0.9031611671},
{"learn":[3.719436563],"iteration":603,"passed_time":1.373435838,"remaining_time":0.9004645559},
{"learn":[3.715046574],"iteration":604,"passed_time":1.375223079,"remaining_time":0.8978729191},
{"learn":[3.71443396],"iteration":605,"passed_time":1.376988095,"remaining_time":0.8952694878},
{"learn":[3.712938941],"iteration":606,"passed_time":1.378492176,"remaining_time":0.892499877},
{"learn":[3.712814764],"iteration":607,"passed_time":1.379839538,"remaining_time":0.8896333862},
{"learn":[3.71235348],"iteration":608,"passed_time":1.384433108,"remaining_time":0.8888560674},
{"learn":[3.711223749],"iteration":609,"passed_time":1.387383612,"remaining_time":0.8870157522},
{"learn":[3.710755648],"iteration":610,"passed_time":1.389307554,"remaining_time":0.8845182302},
{"learn":[3.708668039],"iteration":611,"passed_time":1.391124521,"remaining_time":0.8819547615},
{"learn":[3.705623591],"iteration":612,"passed_time":1.39311698,"remaining_time":0.8795045208},
{"learn":[3.704045802],"iteration":613,"passed_time":1.394897758,"remaining_time":0.8769226951},
{"learn":[3.699915209],"iteration":614,"passed_time":1.398226482,"remaining_time":0.8753125132},
{"learn":[3.696182221],"iteration":615,"passed_time":1.400658389,"remaining_time":0.8731376969},
{"learn":[3.694263278],"iteration":616,"passed_time":1.402601007,"remaining_time":0.8706583234},
{"learn":[3.693810229],"iteration":617,"passed_time":1.40436654,"remaining_time":0.8680712269},
{"learn":[3.690900932],"iteration":618,"passed_time":1.406068862,"remaining_time":0.8654478776},
{"learn":[3.688020895],"iteration":619,"passed_time":1.407913087,"remaining_time":0.8629144729},
{"learn":[3.685491894],"iteration":620,"passed_time":1.409781003,"remaining_time":0.8603977457},
{"learn":[3.684328128],"iteration":621,"passed_time":1.41151867,"remaining_time":0.8578039507},
{"learn":[3.680640153],"iteration":622,"passed_time":1.415393483,"remaining_time":0.8565061687},
{"learn":[3.678932783],"iteration":623,"passed_time":1.417164531,"remaining_time":0.8539324738},
{"learn":[3.674167041],"iteration":624,"passed_time":1.418886614,"remaining_time":0.8513319687},
{"learn":[3.672200976],"iteration":625,"passed_time":1.420518775,"remaining_time":0.8486805459},
{"learn":[3.670606604],"iteration":626,"passed_time":1.422067041,"remaining_time":0.845982466},
{"learn":[3.665506042],"iteration":627,"passed_time":1.424448647,"remaining_time":0.8437816826},
{"learn":[3.664214007],"iteration":628,"passed_time":1.42725654,"remaining_time":0.841831759},
{"learn":[3.66261643],"iteration":629,"passed_time":1.430660988,"remaining_time":0.8402294692},
{"learn":[3.662118449],"iteration":630,"passed_time":1.432530502,"remaining_time":0.8377238595},
{"learn":[3.660871366],"iteration":631,"passed_time":1.434115301,"remaining_time":0.835054479},
{"learn":[3.656695243],"iteration":632,"passed_time":1.43617766,"remaining_time":0.8326654046},
{"learn":[3.654497801],"iteration":633,"passed_time":1.437932244,"remaining_time":0.8300996868},
{"learn":[3.654189134],"iteration":634,"passed_time":1.439955995,"remaining_time":0.8276912413},
{"learn":[3.653957699],"iteration":635,"passed_time":1.443713161,"remaining_time":0.826276086},
{"learn":[3.651920725],"iteration":636,"passed_time":1.446112215,"remaining_time":0.8240796451},
{"learn":[3.65106705],"iteration":637,"passed_time":1.448027728,"remaining_time":0.8216082094},
{"learn":[3.650612844],"iteration":638,"passed_time":1.449776005,"remaining_time":0.819044034},
{"learn":[3.649884732],"iteration":639,"passed_time":1.451420929,"remaining_time":0.8164242728},
{"learn":[3.646276182],"iteration":640,"passed_time":1.453190747,"remaining_time":0.8138775009},
{"learn":[3.645808194],"iteration":641,"passed_time":1.455231845,"remaining_time":0.8114844246},
{"learn":[3.645042989],"iteration":642,"passed_time":1.460885592,"remaining_time":0.8110982213},
{"learn":[3.639864499],"iteration":643,"passed_time":1.463514285,"remaining_time":0.8090234248},
{"learn":[3.637318478],"iteration":644,"passed_time":1.465544394,"remaining_time":0.8066174571},
{"learn":[3.636344905],"iteration":645,"passed_time":1.467175434,"remaining_time":0.8039939684},
{"learn":[3.634754643],"iteration":646,"passed_time":1.468935489,"remaining_time":0.8014439378},
{"learn":[3.630724975],"iteration":647,"passed_time":1.47107359,"remaining_time":0.7991017033},
{"learn":[3.629408252],"iteration":648,"passed_time":1.476298436,"remaining_time":0.7984295086},
{"learn":[3.62790646],"iteration":649,"passed_time":1.478109892,"remaining_time":0.7959053265},
{"learn":[3.627388973],"iteration":650,"passed_time":1.479886969,"remaining_time":0.7933649037},
{"learn":[3.625163557],"iteration":651,"passed_time":1.481594948,"remaining_time":0.7907899416},
{"learn":[3.623701985],"iteration":652,"passed_time":1.483761103,"remaining_time":0.788461107},
{"learn":[3.622342639],"iteration":653,"passed_time":1.485336647,"remaining_time":0.7858203054},
{"learn":[3.621130639],"iteration":654,"passed_time":1.488573486,"remaining_time":0.7840577903},
{"learn":[3.619125665],"iteration":655,"passed_time":1.491562728,"remaining_time":0.7821609426},
{"learn":[3.618878783],"iteration":656,"passed_time":1.49357956,"remaining_time":0.7797531034},
{"learn":[3.616207429],"iteration":657,"passed_time":1.495313234,"remaining_time":0.7771992794},
{"learn":[3.61206486],"iteration":658,"passed_time":1.497162674,"remaining_time":0.7747078481},
{"learn":[3.611955873],"iteration":659,"passed_time":1.499183869,"remaining_time":0.7723068418},
{"learn":[3.610713743],"iteration":660,"passed_time":1.503273373,"remaining_time":0.7709677358},
{"learn":[3.610044025],"iteration":661,"passed_time":1.505821195,"remaining_time":0.7688331782},
{"learn":[3.607342669],"iteration":662,"passed_time":1.507538141,"remaining_time":0.7662750428},
{"learn":[3.602510618],"iteration":663,"passed_time":1.509199028,"remaining_time":0.7636910745},
{"learn":[3.600492392],"iteration":664,"passed_time":1.511011523,"remaining_time":0.7611862558},
{"learn":[3.597171065],"iteration":665,"passed_time":1.51308389,"remaining_time":0.7588138428},
{"learn":[3.594358798],"iteration":666,"passed_time":1.514599918,"remaining_time":0.7561645767},
{"learn":[3.593945251],"iteration":667,"passed_time":1.519613336,"remaining_time":0.7552569274},
{"learn":[3.593607748],"iteration":668,"passed_time":1.521299077,"remaining_time":0.7526905748},
{"learn":[3.592238714],"iteration":669,"passed_time":1.523077498,"remaining_time":0.750172499},
{"learn":[3.590144654],"iteration":670,"passed_time":1.526291729,"remaining_time":0.7483606243},
{"learn":[3.587151536],"iteration":671,"passed_time":1.527865515,"remaining_time":0.7457438825},
{"learn":[3.586070865],"iteration":672,"passed_time":1.529342527,"remaining_time":0.7430832187},
{"learn":[3.585102746],"iteration":673,"passed_time":1.533364802,"remaining_time":0.7416571595},
{"learn":[3.584362847],"iteration":674,"passed_time":1.53535057,"remaining_time":0.739242867},
{"learn":[3.581407561],"iteration":675,"passed_time":1.53715168,"remaining_time":0.7367413376},
{"learn":[3.57919422],"iteration":676,"passed_time":1.538765312,"remaining_time":0.734152431},
{"learn":[3.577632204],"iteration":677,"passed_time":1.540361664,"remaining_time":0.7315581944},
{"learn":[3.573911195],"iteration":678,"passed_time":1.541750421,"remaining_time":0.7288687559},
{"learn":[3.573408216],"iteration":679,"passed_time":1.543098242,"remaining_time":0.7261638784},
{"learn":[3.571076482],"iteration":680,"passed_time":1.544968558,"remaining_time":0.7237077385},
{"learn":[3.568177107],"iteration":681,"passed_time":1.549084659,"remaining_time":0.7223004715},
{"learn":[3.564824621],"iteration":682,"passed_time":1.550753822,"remaining_time":0.7197495776},
{"learn":[3.562475026],"iteration":683,"passed_time":1.552417045,"remaining_time":0.717198518},
{"learn":[3.561226889],"iteration":684,"passed_time":1.553944395,"remaining_time":0.7145875684},
{"learn":[3.559383467],"iteration":685,"passed_time":1.556219028,"remaining_time":0.7123218292},
{"learn":[3.555209766],"iteration":686,"passed_time":1.55787218,"remaining_time":0.7097729145},
{"learn":[3.55345383],"iteration":687,"passed_time":1.559578195,"remaining_time":0.7072505768},
{"learn":[3.552300968],"iteration":688,"passed_time":1.563803526,"remaining_time":0.7058677745},
{"learn":[3.551253986],"iteration":689,"passed_time":1.565566531,"remaining_time":0.7033704703},
{"learn":[3.549807725],"iteration":690,"passed_time":1.567235109,"remaining_time":0.7008330663},
{"learn":[3.547992926],"iteration":691,"passed_time":1.569696391,"remaining_time":0.698650995},
{"learn":[3.545438607],"iteration":692,"passed_time":1.571886071,"remaining_time":0.6963477978},
{"learn":[3.543313763],"iteration":693,"passed_time":1.573619383,"remaining_time":0.6938437048},
{"learn":[3.542962896],"iteration":694,"passed_time":1.575420152,"remaining_time":0.6913714337},
{"learn":[3.539800465],"iteration":695,"passed_time":1.579195671,"remaining_time":0.6897636264},
{"learn":[3.53953187],"iteration":696,"passed_time":1.581275278,"remaining_time":0.6874123519},
{"learn":[3.536332425],"iteration":697,"passed_time":1.583330988,"remaining_time":0.6850515165},
{"learn":[3.534993327],"iteration":698,"passed_time":1.585102337,"remaining_time":0.6825691036},
{"learn":[3.531637011],"iteration":699,"passed_time":1.588498902,"remaining_time":0.6807852439},
{"learn":[3.531040284],"iteration":700,"passed_time":1.590355535,"remaining_time":0.67833995},
{"learn":[3.529973872],"iteration":701,"passed_time":1.59492055,"remaining_time":0.6770460454},
{"learn":[3.527325183],"iteration":702,"passed_time":1.596624757,"remaining_time":0.6745342144},
{"learn":[3.527200815],"iteration":703,"passed_time":1.598419123,"remaining_time":0.6720625857},
{"learn":[3.523459911],"iteration":704,"passed_time":1.600340511,"remaining_time":0.6696460296},
{"learn":[3.522729934],"iteration":705,"passed_time":1.602036775,"remaining_time":0.6671371273},
{"learn":[3.522260582],"iteration":706,"passed_time":1.604194828,"remaining_time":0.6648219019},
{"learn":[3.518641591],"iteration":707,"passed_time":1.609011236,"remaining_time":0.6636035041},
{"learn":[3.516856405],"iteration":708,"passed_time":1.610721364,"remaining_time":0.661100024},
{"learn":[3.515083413],"iteration":709,"passed_time":1.614870915,"remaining_time":0.6595951627},
{"learn":[3.514671214],"iteration":710,"passed_time":1.617143238,"remaining_time":0.6573198255},
{"learn":[3.512617621],"iteration":711,"passed_time":1.619144297,"remaining_time":0.6549347718},
{"learn":[3.510747971],"iteration":712,"passed_time":1.625073359,"remaining_time":0.654131913},
{"learn":[3.508149266],"iteration":713,"passed_time":1.627366202,"remaining_time":0.6518581707},
{"learn":[3.504557165],"iteration":714,"passed_time":1.629161749,"remaining_time":0.6493861518},
{"learn":[3.501367208],"iteration":715,"passed_time":1.631004974,"remaining_time":0.6469349337},
{"learn":[3.497593362],"iteration":716,"passed_time":1.632970345,"remaining_time":0.6445336231},
{"learn":[3.496291169],"iteration":717,"passed_time":1.635081163,"remaining_time":0.6421906518},
{"learn":[3.49330374],"iteration":718,"passed_time":1.639816735,"remaining_time":0.6408741342},
{"learn":[3.490044385],"iteration":719,"passed_time":1.641693666,"remaining_time":0.6384364259},
{"learn":[3.488891789],"iteration":720,"passed_time":1.643671185,"remaining_time":0.6360391966},
{"learn":[3.486869081],"iteration":721,"passed_time":1.645348007,"remaining_time":0.6335273491},
{"learn":[3.486303638],"iteration":722,"passed_time":1.647725858,"remaining_time":0.6312863936},
{"learn":[3.486035862],"iteration":723,"passed_time":1.649890535,"remaining_time":0.628963795},
{"learn":[3.482668951],"iteration":724,"passed_time":1.654342365,"remaining_time":0.6275091731},
{"learn":[3.47820549],"iteration":725,"passed_time":1.656746322,"remaining_time":0.6252734053},
{"learn":[3.474392283],"iteration":726,"passed_time":1.658633564,"remaining_time":0.6228431402},
{"learn":[3.472268163],"iteration":727,"passed_time":1.660364306,"remaining_time":0.6203558947},
{"learn":[3.471209164],"iteration":728,"passed_time":1.662654516,"remaining_time":0.6180787021},
{"learn":[3.470049971],"iteration":729,"passed_time":1.664414908,"remaining_time":0.6156055141},
{"learn":[3.469078654],"iteration":730,"passed_time":1.667843252,"remaining_time":0.6137480641},
{"learn":[3.468643292],"iteration":731,"passed_time":1.669814423,"remaining_time":0.6113528214},
{"learn":[3.468134848],"iteration":732,"passed_time":1.67150751,"remaining_time":0.6088574422},
{"learn":[3.467820182],"iteration":733,"passed_time":1.673424099,"remaining_time":0.6064452457},
{"learn":[3.465776156],"iteration":734,"passed_time":1.675159041,"remaining_time":0.6039689058},
{"learn":[3.463037608],"iteration":735,"passed_time":1.67690107,"remaining_time":0.6014971228},
{"learn":[3.45965637],"iteration":736,"passed_time":1.678443893,"remaining_time":0.5989562331},
{"learn":[3.457275091],"iteration":737,"passed_time":1.684011413,"remaining_time":0.5978468702},
{"learn":[3.455522955],"iteration":738,"passed_time":1.685938503,"remaining_time":0.595439715},
{"learn":[3.451270508],"iteration":739,"passed_time":1.687932488,"remaining_time":0.5930573607},
{"learn":[3.450978947],"iteration":740,"passed_time":1.69009466,"remaining_time":0.5907348407},
{"learn":[3.450608492],"iteration":741,"passed_time":1.692038973,"remaining_time":0.5883370013},
{"learn":[3.448122004],"iteration":742,"passed_time":1.694188679,"remaining_time":0.5860114274},
{"learn":[3.445646714],"iteration":743,"passed_time":1.699201363,"remaining_time":0.5846714369},
{"learn":[3.44411263],"iteration":744,"passed_time":1.702123755,"remaining_time":0.5826061174},
{"learn":[3.443264164],"iteration":745,"passed_time":1.703895136,"remaining_time":0.5801466014},
{"learn":[3.439521363],"iteration":746,"passed_time":1.705883336,"remaining_time":0.5777623614},
{"learn":[3.436809225],"iteration":747,"passed_time":1.707652409,"remaining_time":0.5753053569},
{"learn":[3.435509465],"iteration":748,"passed_time":1.710231683,"remaining_time":0.573121699},
{"learn":[3.434450277],"iteration":749,"passed_time":1.714508452,"remaining_time":0.5715028173},
{"learn":[3.431786753],"iteration":750,"passed_time":1.716593988,"remaining_time":0.5691503369},
{"learn":[3.430150302],"iteration":751,"passed_time":1.718208015,"remaining_time":0.5666430687},
{"learn":[3.42696281],"iteration":752,"passed_time":1.719950912,"remaining_time":0.5641804453},
{"learn":[3.426870334],"iteration":753,"passed_time":1.721618648,"remaining_time":0.5616952087},
{"learn":[3.425200309],"iteration":754,"passed_time":1.723372214,"remaining_time":0.55923999},
{"learn":[3.423383783],"iteration":755,"passed_time":1.726364898,"remaining_time":0.5571865545},
{"learn":[3.422752979],"iteration":756,"passed_time":1.728131355,"remaining_time":0.5547370135},
{"learn":[3.420845924],"iteration":757,"passed_time":1.729883727,"remaining_time":0.5522847782},
{"learn":[3.418917862],"iteration":758,"passed_time":1.731337074,"remaining_time":0.54973944},
{"learn":[3.417095735],"iteration":759,"passed_time":1.732866385,"remaining_time":0.5472209637},
{"learn":[3.414391848],"iteration":760,"passed_time":1.734322547,"remaining_time":0.5446821139},
{"learn":[3.41426711],"iteration":761,"passed_time":1.735763988,"remaining_time":0.5421415079},
{"learn":[3.411976013],"iteration":762,"passed_time":1.737381651,"remaining_time":0.5396585208},
{"learn":[3.408614844],"iteration":763,"passed_time":1.740744374,"remaining_time":0.5377168484},
{"learn":[3.407906721],"iteration":764,"passed_time":1.743094687,"remaining_time":0.5354604593},
{"learn":[3.407494015],"iteration":765,"passed_time":1.744641673,"remaining_time":0.5329584222},
{"learn":[3.406287128],"iteration":766,"passed_time":1.746053356,"remaining_time":0.5304177732},
{"learn":[3.404600442],"iteration":767,"passed_time":1.747506055,"remaining_time":0.5278924543},
{"learn":[3.404012662],"iteration":768,"passed_time":1.749050454,"remaining_time":0.5253974707},
{"learn":[3.400398762],"iteration":769,"passed_time":1.750585293,"remaining_time":0.5229021005},
{"learn":[3.399737714],"iteration":770,"passed_time":1.752121995,"remaining_time":0.5204097754},
{"learn":[3.399185251],"iteration":771,"passed_time":1.753859494,"remaining_time":0.5179792287},
{"learn":[3.397245411],"iteration":772,"passed_time":1.756912784,"remaining_time":0.5159368718},
{"learn":[3.396229831],"iteration":773,"passed_time":1.758434242,"remaining_time":0.5134446236},
{"learn":[3.394002836],"iteration":774,"passed_time":1.759997989,"remaining_time":0.5109671581},
{"learn":[3.389617243],"iteration":775,"passed_time":1.76166265,"remaining_time":0.5085211772},
{"learn":[3.385426488],"iteration":776,"passed_time":1.763075358,"remaining_time":0.5060048967},
{"learn":[3.385072258],"iteration":777,"passed_time":1.764612341,"remaining_time":0.5035269147},
{"learn":[3.383842366],"iteration":778,"passed_time":1.766063983,"remaining_time":0.5010271376},
{"learn":[3.380110746],"iteration":779,"passed_time":1.767678267,"remaining_time":0.4985759215},
{"learn":[3.378595218],"iteration":780,"passed_time":1.771066449,"remaining_time":0.4966242667},
{"learn":[3.377371219],"iteration":781,"passed_time":1.773261297,"remaining_time":0.4943362695},
{"learn":[3.375814782],"iteration":782,"passed_time":1.774808276,"remaining_time":0.4918689603},
{"learn":[3.374195887],"iteration":783,"passed_time":1.776256689,"remaining_time":0.4893768428},
{"learn":[3.373704309],"iteration":784,"passed_time":1.777941034,"remaining_time":0.4869520028},
{"learn":[3.372971757],"iteration":785,"passed_time":1.779751068,"remaining_time":0.484563268},
{"learn":[3.371565136],"iteration":786,"passed_time":1.783471438,"remaining_time":0.4826930322},
{"learn":[3.3700309],"iteration":787,"passed_time":1.78709326,"remaining_time":0.4807915878},
{"learn":[3.368186663],"iteration":788,"passed_time":1.788875339,"remaining_time":0.4783937851},
{"learn":[3.366710398],"iteration":789,"passed_time":1.790521284,"remaining_time":0.475961354},
{"learn":[3.364598042],"iteration":790,"passed_time":1.792084324,"remaining_time":0.4735090059},
{"learn":[3.36348442],"iteration":791,"passed_time":1.793508119,"remaining_time":0.4710223344},
{"learn":[3.362001759],"iteration":792,"passed_time":1.795043947,"remaining_time":0.4685675877},
{"learn":[3.361580401],"iteration":793,"passed_time":1.797172039,"remaining_time":0.4662688162},
{"learn":[3.359543675],"iteration":794,"passed_time":1.799986043,"remaining_time":0.4641473443},
{"learn":[3.35766119],"iteration":795,"passed_time":1.802928382,"remaining_time":0.4620570225},
{"learn":[3.354592969],"iteration":796,"passed_time":1.804760991,"remaining_time":0.4596819085},
{"learn":[3.350985986],"iteration":797,"passed_time":1.806297648,"remaining_time":0.4572332391},
{"learn":[3.349589624],"iteration":798,"passed_time":1.807782815,"remaining_time":0.4547738997},
{"learn":[3.349110856],"iteration":799,"passed_time":1.809819925,"remaining_time":0.4524549813},
{"learn":[3.345315441],"iteration":800,"passed_time":1.811517322,"remaining_time":0.4500523684},
{"learn":[3.34397474],"iteration":801,"passed_time":1.813007195,"remaining_time":0.44760028},
{"learn":[3.343800902],"iteration":802,"passed_time":1.819278206,"remaining_time":0.446323545},
{"learn":[3.342329465],"iteration":803,"passed_time":1.820881821,"remaining_time":0.4438965633},
{"learn":[3.34220347],"iteration":804,"passed_time":1.822317308,"remaining_time":0.4414309007},
{"learn":[3.341279219],"iteration":805,"passed_time":1.823777325,"remaining_time":0.4389736986},
{"learn":[3.337329521],"iteration":806,"passed_time":1.825155017,"remaining_time":0.4364992791},
{"learn":[3.336708453],"iteration":807,"passed_time":1.826769342,"remaining_time":0.434083804},
{"learn":[3.333252703],"iteration":808,"passed_time":1.828310761,"remaining_time":0.4316530969},
{"learn":[3.332186769],"iteration":809,"passed_time":1.832147605,"remaining_time":0.4297630184},
{"learn":[3.330594851],"iteration":810,"passed_time":1.835067439,"remaining_time":0.427654434},
{"learn":[3.327867442],"iteration":811,"passed_time":1.836798698,"remaining_time":0.425268664},
{"learn":[3.327563111],"iteration":812,"passed_time":1.83833143,"remaining_time":0.4228388405},
{"learn":[3.326308994],"iteration":813,"passed_time":1.840240231,"remaining_time":0.4204971535},
{"learn":[3.326249879],"iteration":814,"passed_time":1.8418513,"remaining_time":0.4180889454},
{"learn":[3.322336238],"iteration":815,"passed_time":1.843296798,"remaining_time":0.4156453564},
{"learn":[3.320491154],"iteration":816,"passed_time":1.849019251,"remaining_time":0.4141622067},
{"learn":[3.320434271],"iteration":817,"passed_time":1.850960406,"remaining_time":0.4118273765},
{"learn":[3.319609638],"iteration":818,"passed_time":1.852870558,"remaining_time":0.4094866556},
{"learn":[3.316182682],"iteration":819,"passed_time":1.854453848,"remaining_time":0.4070752349},
{"learn":[3.313126612],"iteration":820,"passed_time":1.856095461,"remaining_time":0.4046785474},
{"learn":[3.311222803],"iteration":821,"passed_time":1.858331134,"remaining_time":0.402412338},
{"learn":[3.309627335],"iteration":822,"passed_time":1.863353099,"remaining_time":0.4007454417},
{"learn":[3.307974895],"iteration":823,"passed_time":1.865321862,"remaining_time":0.3984182617},
{"learn":[3.307321505],"iteration":824,"passed_time":1.867165602,"remaining_time":0.3960654306},
{"learn":[3.306759087],"iteration":825,"passed_time":1.868783745,"remaining_time":0.3936663094},
{"learn":[3.30484037],"iteration":826,"passed_time":1.870336387,"remaining_time":0.3912553747},
{"learn":[3.30201994],"iteration":827,"passed_time":1.872061758,"remaining_time":0.3888823941},
{"learn":[3.299302297],"iteration":828,"passed_time":1.877132855,"remaining_time":0.3872011076},
{"learn":[3.298132671],"iteration":829,"passed_time":1.880246319,"remaining_time":0.3851106918},
{"learn":[3.296976183],"iteration":830,"passed_time":1.882302669,"remaining_time":0.3828028292},
{"learn":[3.293144745],"iteration":831,"passed_time":1.885548326,"remaining_time":0.3807357197},
{"learn":[3.290284404],"iteration":832,"passed_time":1.88725993,"remaining_time":0.3783582333},
{"learn":[3.288285745],"iteration":833,"passed_time":1.889368063,"remaining_time":0.376061269},
{"learn":[3.286662667],"iteration":834,"passed_time":1.895576336,"remaining_time":0.3745749646},
{"learn":[3.285692682],"iteration":835,"passed_time":1.897465586,"remaining_time":0.372230091},
{"learn":[3.284565611],"iteration":836,"passed_time":1.898954971,"remaining_time":0.3698084352},
{"learn":[3.283897383],"iteration":837,"passed_time":1.900437265,"remaining_time":0.3673876336},
{"learn":[3.280712855],"iteration":838,"passed_time":1.902362979,"remaining_time":0.3650541593},
{"learn":[3.280468341],"iteration":839,"passed_time":1.90857146,"remaining_time":0.363537421},
{"learn":[3.277814895],"iteration":840,"passed_time":1.910741227,"remaining_time":0.3612459633},
{"learn":[3.276316385],"iteration":841,"passed_time":1.912451631,"remaining_time":0.3588685959},
{"learn":[3.27557063],"iteration":842,"passed_time":1.914080525,"remaining_time":0.3564776303},
{"learn":[3.27499628],"iteration":843,"passed_time":1.915782822,"remaining_time":0.3541020382},
{"learn":[3.273569958],"iteration":844,"passed_time":1.91767767,"remaining_time":0.3517633596},
{"learn":[3.269665595],"iteration":845,"passed_time":1.922101168,"remaining_time":0.3498860282},
{"learn":[3.267984685],"iteration":846,"passed_time":1.924577956,"remaining_time":0.3476510358},
{"learn":[3.267702508],"iteration":847,"passed_time":1.926323648,"remaining_time":0.3452844274},
{"learn":[3.266671924],"iteration":848,"passed_time":1.928114141,"remaining_time":0.34292725},
{"learn":[3.265359825],"iteration":849,"passed_time":1.93028266,"remaining_time":0.3406381164},
{"learn":[3.2618983],"iteration":850,"passed_time":1.93181419,"remaining_time":0.3382377372},
{"learn":[3.260456253],"iteration":851,"passed_time":1.933426706,"remaining_time":0.3358534653},
{"learn":[3.258389147],"iteration":852,"passed_time":1.9386474,"remaining_time":0.334092811},
{"learn":[3.258108469],"iteration":853,"passed_time":1.940731767,"remaining_time":0.3317878665},
{"learn":[3.256424936],"iteration":854,"passed_time":1.942436463,"remaining_time":0.3294190493},
{"learn":[3.254817983],"iteration":855,"passed_time":1.944132281,"remaining_time":0.3270502902},
{"learn":[3.253898449],"iteration":856,"passed_time":1.9457635,"remaining_time":0.3246723226},
{"learn":[3.253023652],"iteration":857,"passed_time":1.947441676,"remaining_time":0.3223038672},
{"learn":[3.252845542],"iteration":858,"passed_time":1.949364778,"remaining_time":0.319977222},
{"learn":[3.252316026],"iteration":859,"passed_time":1.952823791,"remaining_time":0.3179015474},
{"learn":[3.24975301],"iteration":860,"passed_time":1.954463938,"remaining_time":0.3155290214},
{"learn":[3.249151075],"iteration":861,"passed_time":1.956111035,"remaining_time":0.3131593073},
{"learn":[3.246257135],"iteration":862,"passed_time":1.957556539,"remaining_time":0.3107592651},
{"learn":[3.243826471],"iteration":863,"passed_time":1.959273387,"remaining_time":0.3084041443},
{"learn":[3.243190653],"iteration":864,"passed_time":1.960749393,"remaining_time":0.3060129111},
{"learn":[3.24008797],"iteration":865,"passed_time":1.962248153,"remaining_time":0.3036273124},
{"learn":[3.240036811],"iteration":866,"passed_time":1.963741516,"remaining_time":0.3012429315},
{"learn":[3.238676314],"iteration":867,"passed_time":1.968937001,"remaining_time":0.2994235992},
{"learn":[3.237848782],"iteration":868,"passed_time":1.970915735,"remaining_time":0.2971115781},
{"learn":[3.236405498],"iteration":869,"passed_time":1.972536723,"remaining_time":0.2947468666},
{"learn":[3.233378068],"iteration":870,"passed_time":1.974151174,"remaining_time":0.2923828949},
{"learn":[3.233169169],"iteration":871,"passed_time":1.975698398,"remaining_time":0.290010774},
{"learn":[3.232434885],"iteration":872,"passed_time":1.978264181,"remaining_time":0.2877887182},
{"learn":[3.229978115],"iteration":873,"passed_time":1.980220438,"remaining_time":0.2854780036},
{"learn":[3.229648848],"iteration":874,"passed_time":1.983441338,"remaining_time":0.2833487625},
{"learn":[3.227208761],"iteration":875,"passed_time":1.986550986,"remaining_time":0.2812012811},
{"learn":[3.226258869],"iteration":876,"passed_time":1.988213309,"remaining_time":0.2788486168},
{"learn":[3.225331995],"iteration":877,"passed_time":1.989999839,"remaining_time":0.2765147839},
{"learn":[3.221968268],"iteration":878,"passed_time":1.993280997,"remaining_time":0.2743879416},
{"learn":[3.221166317],"iteration":879,"passed_time":1.999364004,"remaining_time":0.272640546},
{"learn":[3.220047503],"iteration":880,"passed_time":2.001262568,"remaining_time":0.2703180995},
{"learn":[3.21982781],"iteration":881,"passed_time":2.003188692,"remaining_time":0.2680003012},
{"learn":[3.216693405],"iteration":882,"passed_time":2.004841276,"remaining_time":0.2656471453},
{"learn":[3.214798761],"iteration":883,"passed_time":2.006422406,"remaining_time":0.2632861981},
{"learn":[3.214395085],"iteration":884,"passed_time":2.008167273,"remaining_time":0.2609482897},
{"learn":[3.213470696],"iteration":885,"passed_time":2.009812048,"remaining_time":0.2585988414},
{"learn":[3.211595017],"iteration":886,"passed_time":2.01366789,"remaining_time":0.2565326625},
{"learn":[3.210965255],"iteration":887,"passed_time":2.015792971,"remaining_time":0.2542441586},
{"learn":[3.209413583],"iteration":888,"passed_time":2.017668807,"remaining_time":0.2519249017},
{"learn":[3.208331683],"iteration":889,"passed_time":2.019079427,"remaining_time":0.2495491427},
{"learn":[3.207110711],"iteration":890,"passed_time":2.020549295,"remaining_time":0.2471827982},
{"learn":[3.204519413],"iteration":891,"passed_time":2.022620251,"remaining_time":0.2448912412},
{"learn":[3.201421296],"iteration":892,"passed_time":2.024017148,"remaining_time":0.2425194119},
{"learn":[3.200691259],"iteration":893,"passed_time":2.02938591,"remaining_time":0.2406207008},
{"learn":[3.200485067],"iteration":894,"passed_time":2.031115101,"remaining_time":0.2382872465},
{"learn":[3.197467568],"iteration":895,"passed_time":2.032682124,"remaining_time":0.2359363179},
{"learn":[3.195838544],"iteration":896,"passed_time":2.034102675,"remaining_time":0.2335703184},
{"learn":[3.195671746],"iteration":897,"passed_time":2.035498772,"remaining_time":0.2312036467},
{"learn":[3.194213094],"iteration":898,"passed_time":2.03685577,"remaining_time":0.2288347417},
{"learn":[3.192884691],"iteration":899,"passed_time":2.038584435,"remaining_time":0.2265093816},
{"learn":[3.188364239],"iteration":900,"passed_time":2.042175775,"remaining_time":0.2243900131},
{"learn":[3.185219478],"iteration":901,"passed_time":2.044451044,"remaining_time":0.2221243928},
{"learn":[3.184120387],"iteration":902,"passed_time":2.046070573,"remaining_time":0.2197883118},
{"learn":[3.183725321],"iteration":903,"passed_time":2.047598866,"remaining_time":0.2174441274},
{"learn":[3.181264554],"iteration":904,"passed_time":2.049093522,"remaining_time":0.215098215},
{"learn":[3.180741589],"iteration":905,"passed_time":2.050548532,"remaining_time":0.2127500685},
{"learn":[3.179782639],"iteration":906,"passed_time":2.051948518,"remaining_time":0.2103982494},
{"learn":[3.176377564],"iteration":907,"passed_time":2.053314298,"remaining_time":0.2080450611},
{"learn":[3.174078182],"iteration":908,"passed_time":2.054638464,"remaining_time":0.2056898792},
{"learn":[3.171242379],"iteration":909,"passed_time":2.059707061,"remaining_time":0.2037072917},
{"learn":[3.170421012],"iteration":910,"passed_time":2.061433772,"remaining_time":0.2013914442},
{"learn":[3.170087224],"iteration":911,"passed_time":2.06298655,"remaining_time":0.1990601057},
{"learn":[3.167303059],"iteration":912,"passed_time":2.064513946,"remaining_time":0.196728054},
{"learn":[3.16705966],"iteration":913,"passed_time":2.065934499,"remaining_time":0.1943877099},
{"learn":[3.165667683],"iteration":914,"passed_time":2.067699281,"remaining_time":0.192081354},
{"learn":[3.164689733],"iteration":915,"passed_time":2.068984707,"remaining_time":0.1897322221},
{"learn":[3.163311455],"iteration":916,"passed_time":2.07179523,"remaining_time":0.1875234505},
{"learn":[3.159425016],"iteration":917,"passed_time":2.074161682,"remaining_time":0.1852737015},
{"learn":[3.159327058],"iteration":918,"passed_time":2.076067592,"remaining_time":0.1829831066},
{"learn":[3.15819426],"iteration":919,"passed_time":2.078012137,"remaining_time":0.1806967075},
{"learn":[3.157086603],"iteration":920,"passed_time":2.079484956,"remaining_time":0.178370588},
{"learn":[3.153354154],"iteration":921,"passed_time":2.08092551,"remaining_time":0.1760435898},
{"learn":[3.153261317],"iteration":922,"passed_time":2.082686421,"remaining_time":0.1737452377},
{"learn":[3.153168454],"iteration":923,"passed_time":2.084198573,"remaining_time":0.1714275883},
{"learn":[3.152080399],"iteration":924,"passed_time":2.089533904,"remaining_time":0.1694216679},
{"learn":[3.151635144],"iteration":925,"passed_time":2.091367088,"remaining_time":0.1671286874},
{"learn":[3.147762655],"iteration":926,"passed_time":2.093243279,"remaining_time":0.1648400856},
{"learn":[3.147172317],"iteration":927,"passed_time":2.094999705,"remaining_time":0.1625430806},
{"learn":[3.146254125],"iteration":928,"passed_time":2.096722339,"remaining_time":0.1602446567},
{"learn":[3.144869828],"iteration":929,"passed_time":2.098824921,"remaining_time":0.1579760693},
{"learn":[3.143466218],"iteration":930,"passed_time":2.10191365,"remaining_time":0.1557809257},
{"learn":[3.141919643],"iteration":931,"passed_time":2.104858635,"remaining_time":0.1535733768},
{"learn":[3.141054135],"iteration":932,"passed_time":2.106654328,"remaining_time":0.1512817149},
{"learn":[3.139390417],"iteration":933,"passed_time":2.108280197,"remaining_time":0.1489791146},
{"learn":[3.139025283],"iteration":934,"passed_time":2.109688629,"remaining_time":0.1466628458},
{"learn":[3.137824183],"iteration":935,"passed_time":2.111070105,"remaining_time":0.1443466738},
{"learn":[3.135620453],"iteration":936,"passed_time":2.112933483,"remaining_time":0.142064898},
{"learn":[3.13443178],"iteration":937,"passed_time":2.114547411,"remaining_time":0.1397675261},
{"learn":[3.132765713],"iteration":938,"passed_time":2.118963021,"remaining_time":0.1376536148},
{"learn":[3.131434124],"iteration":939,"passed_time":2.121826871,"remaining_time":0.1354357577},
{"learn":[3.128384262],"iteration":940,"passed_time":2.123622971,"remaining_time":0.1331495805},
{"learn":[3.128120455],"iteration":941,"passed_time":2.125339006,"remaining_time":0.1308595142},
{"learn":[3.126314615],"iteration":942,"passed_time":2.12688019,"remaining_time":0.1285600963},
{"learn":[3.125409666],"iteration":943,"passed_time":2.128493913,"remaining_time":0.1262665881},
{"learn":[3.123072589],"iteration":944,"passed_time":2.130777401,"remaining_time":0.1240134995},
{"learn":[3.122921099],"iteration":945,"passed_time":2.134305596,"remaining_time":0.1218313977},
{"learn":[3.122182662],"iteration":946,"passed_time":2.13622544,"remaining_time":0.1195564396},
{"learn":[3.120040951],"iteration":947,"passed_time":2.139318585,"remaining_time":0.1173465891},
{"learn":[3.118767799],"iteration":948,"passed_time":2.141193902,"remaining_time":0.1150694299},
{"learn":[3.118203218],"iteration":949,"passed_time":2.14332613,"remaining_time":0.1128066384},
{"learn":[3.116343362],"iteration":950,"passed_time":2.14745482,"remaining_time":0.1106469886},
{"learn":[3.11480829],"iteration":951,"passed_time":2.149730778,"remaining_time":0.1083897871},
{"learn":[3.112607903],"iteration":952,"passed_time":2.151414673,"remaining_time":0.1061033469},
{"learn":[3.111661241],"iteration":953,"passed_time":2.15310121,"remaining_time":0.1038182973},
{"learn":[3.110249676],"iteration":954,"passed_time":2.154853601,"remaining_time":0.1015376042},
{"learn":[3.107333579],"iteration":955,"passed_time":2.156578593,"remaining_time":0.09925675531},
{"learn":[3.107149851],"iteration":956,"passed_time":2.158281987,"remaining_time":0.09697609766},
{"learn":[3.106867336],"iteration":957,"passed_time":2.159790427,"remaining_time":0.09468809804},
{"learn":[3.10364681],"iteration":958,"passed_time":2.163940089,"remaining_time":0.09251464406},
{"learn":[3.102703811],"iteration":959,"passed_time":2.165738034,"remaining_time":0.09023908475},
{"learn":[3.101469264],"iteration":960,"passed_time":2.167313563,"remaining_time":0.08795549319},
{"learn":[3.09863569],"iteration":961,"passed_time":2.168940074,"remaining_time":0.08567538752},
{"learn":[3.09645939],"iteration":962,"passed_time":2.170829475,"remaining_time":0.08340673995},
{"learn":[3.096240186],"iteration":963,"passed_time":2.172809199,"remaining_time":0.08114225225},
{"learn":[3.094838828],"iteration":964,"passed_time":2.174782085,"remaining_time":0.07887810672},
{"learn":[3.094176802],"iteration":965,"passed_time":2.177327183,"remaining_time":0.07663470416},
{"learn":[3.093182279],"iteration":966,"passed_time":2.179324526,"remaining_time":0.07437198485},
{"learn":[3.090150687],"iteration":967,"passed_time":2.181679814,"remaining_time":0.07212164673},
{"learn":[3.088612829],"iteration":968,"passed_time":2.184053816,"remaining_time":0.06987169071},
{"learn":[3.087153684],"iteration":969,"passed_time":2.185961879,"remaining_time":0.06760706841},
{"learn":[3.085866843],"iteration":970,"passed_time":2.187720861,"remaining_time":0.06533872808},
{"learn":[3.082669094],"iteration":971,"passed_time":2.190256283,"remaining_time":0.06309380238},
{"learn":[3.081047548],"iteration":972,"passed_time":2.192575698,"remaining_time":0.06084228554},
{"learn":[3.079684322],"iteration":973,"passed_time":2.194670529,"remaining_time":0.05858463424},
{"learn":[3.07613431],"iteration":974,"passed_time":2.196239096,"remaining_time":0.05631382297},
{"learn":[3.074005935],"iteration":975,"passed_time":2.197694939,"remaining_time":0.05404167882},
{"learn":[3.072988853],"iteration":976,"passed_time":2.199426809,"remaining_time":0.0517777038},
{"learn":[3.072344268],"iteration":977,"passed_time":2.201500036,"remaining_time":0.04952249569},
{"learn":[3.070654438],"iteration":978,"passed_time":2.202987427,"remaining_time":0.04725509292},
{"learn":[3.069724506],"iteration":979,"passed_time":2.2064721,"remaining_time":0.04503004287},
{"learn":[3.067763166],"iteration":980,"passed_time":2.208608052,"remaining_time":0.04277630273},
{"learn":[3.066737893],"iteration":981,"passed_time":2.210235066,"remaining_time":0.04051347371},
{"learn":[3.065248174],"iteration":982,"passed_time":2.211740957,"remaining_time":0.03824984361},
{"learn":[3.063186837],"iteration":983,"passed_time":2.2132686,"remaining_time":0.03598810731},
{"learn":[3.062880371],"iteration":984,"passed_time":2.214855498,"remaining_time":0.03372876392},
{"learn":[3.061288645],"iteration":985,"passed_time":2.216349946,"remaining_time":0.03146947185},
{"learn":[3.059970575],"iteration":986,"passed_time":2.217784676,"remaining_time":0.02921094305},
{"learn":[3.059576341],"iteration":987,"passed_time":2.222163299,"remaining_time":0.02698983764},
{"learn":[3.058175919],"iteration":988,"passed_time":2.223903533,"remaining_time":0.02473502413},
{"learn":[3.056830702],"iteration":989,"passed_time":2.225683641,"remaining_time":0.02248165294},
{"learn":[3.056336579],"iteration":990,"passed_time":2.227229712,"remaining_time":0.02022711141},
{"learn":[3.055810414],"iteration":991,"passed_time":2.228632477,"remaining_time":0.01797284256},
{"learn":[3.055476518],"iteration":992,"passed_time":2.230168807,"remaining_time":0.01572123026},
{"learn":[3.053331734],"iteration":993,"passed_time":2.232035356,"remaining_time":0.01347305044},
{"learn":[3.050890374],"iteration":994,"passed_time":2.233429147,"remaining_time":0.01122326204},
{"learn":[3.04972623],"iteration":995,"passed_time":2.238509629,"remaining_time":0.008989998511},
{"learn":[3.047217327],"iteration":996,"passed_time":2.240224156,"remaining_time":0.006740895154},
{"learn":[3.047155483],"iteration":997,"passed_time":2.241693545,"remaining_time":0.004492371834},
{"learn":[3.04430671],"iteration":998,"passed_time":2.243134512,"remaining_time":0.002245379892},
{"learn":[3.042664195],"iteration":999,"passed_time":2.244766843,"remaining_time":0}
]}